{
	"code" : 0 ,
	"data" : [
	 
	{
		"title" : "《Mac软件站点》　2024/10/05　Mac-软件-开源",
		"url" : "/article/17280983369"
	}
	
	,
	
    
	{
		"title" : "《定期自动备份又拍云存储》　2024/10/05　图床-备份-又拍云-github-action",
		"url" : "/article/17280983368"
	}
	
	,
	
    
	{
		"title" : "《博客常见问题》　2024/09/17　博客-SEO-收录-常见问题-problem",
		"url" : "/article/17265361548"
	}
	
	,
	
    
	{
		"title" : "《防止网站被恶意镜像》　2024/08/24　镜像-搬运-博客-SEO-收录",
		"url" : "/article/17245056864"
	}
	
	,
	
    
	{
		"title" : "《Follow - 订阅一切》　2024/07/06　Follow-订阅-feed-rss-follow.is",
		"url" : "/article/17202356559"
	}
	
	,
	
    
	{
		"title" : "《双因素认证(2FA)实现原理》　2024/06/29　TOTP-MFA-多因子-二次验证-HOTP",
		"url" : "/article/17196724432"
	}
	
	,
	
    
	{
		"title" : "《衣服的洗涤保养说明》　2024/05/02　衣服-洗涤-保养-水洗-漂白",
		"url" : "/article/17146497169"
	}
	
	,
	
    
	{
		"title" : "《倒计时关闭的JS 公告》　2024/04/06　公告-弹窗-提示-倒计时-warning",
		"url" : "/article/17123887436"
	}
	
	,
	
    
	{
		"title" : "《App更新总提醒缺少出口合规证明》　2024/03/25　App Store Connect-上架-更新-出口-合规证明",
		"url" : "/article/17113627324"
	}
	
	,
	
    
	{
		"title" : "《外链跳转到中间页》　2024/03/03　外链-中间页-安全-博客-gorpeln",
		"url" : "/article/17094338798"
	}
	
	,
	
    
	{
		"title" : "《GitHub贡献者可获取 Stark 空投》　2024/02/24　GitHub-Stark-空投-STRK-欧易",
		"url" : "/article/17087779433"
	}
	
	,
	
    
	{
		"title" : "《部署友链朋友圈》　2024/01/11　友链-朋友圈-Friends-Vercel-爬虫",
		"url" : "/article/17049566482"
	}
	
	,
	
    
	{
		"title" : "《2023 年度总结》　2023/12/31　年度总结-成长-2023-新年-苟活",
		"url" : "/article/17040105944"
	}
	
	,
	
    
	{
		"title" : "《博客黑夜模式：Dark Reader 插件》　2023/12/03　个人博客-黑夜模式-darkreader-插件",
		"url" : "/article/17016025546"
	}
	
	,
	
    
	{
		"title" : "《个性二维码合集》　2023/11/04　个人博客-二维码-个性-扫一扫",
		"url" : "/article/16990919984"
	}
	
	,
	
    
	{
		"title" : "《Sublime Text 常用插件》　2023/10/02　Sublime-插件-备忘-ColorHelper-HTML",
		"url" : "/article/16962230954"
	}
	
	,
	
    
	{
		"title" : "《博客评论时一键填写自己的信息》　2023/09/29　个人博客-昵称-邮箱-网址-一键填写",
		"url" : "/article/16959932733"
	}
	
	,
	
    
	{
		"title" : "《8周年：博海泛舟，共赴时光之旅》　2023/08/23　个人博客-8周年-简洁-高效",
		"url" : "/article/16927632006"
	}
	
	,
	
    
	{
		"title" : "《同一台电脑上使用多个GitHub账号》　2023/07/17　Git-GitHub-SSH-rsa-Sourcetree",
		"url" : "/article/16895899334"
	}
	
	,
	
    
	{
		"title" : "《用 Substats 和 Shields.io 为你的个人主页定制动态数据小牌子》　2023/06/22　Substats-Shields-小牌子-Cloudflare-github",
		"url" : "/article/16874238349"
	}
	
	,
	
    
	{
		"title" : "《个人网站，零成本、低门槛创建专属数据分析工具：umami.is》　2023/05/01　博客-网站-umami-数据分析-Serverless",
		"url" : "/article/16829158558"
	}
	
	,
	
    
	{
		"title" : "《全飞秒近视手术过程和恢复记录》　2023/04/29　全飞秒-近视-手术-眼镜-眼睛",
		"url" : "/article/16827504397"
	}
	
	,
	
    
	{
		"title" : "《高德地图产品使用体验报告》　2023/03/12　高德-地图-体验报告-导航-Amap",
		"url" : "/article/16786112870"
	}
	
	,
	
    
	{
		"title" : "《30张高清地图全面解读中国地理》　2023/02/05　中国-地理-地势-地形-气候-干湿-水系-降水量-土地资源-水资源-海洋资源-新能源-沙尘暴-旅游资源",
		"url" : "/article/16755875711"
	}
	
	,
	
    
	{
		"title" : "《下载神器：Aria2搭建》　2023/01/02　Mac-Aria2-BT下载-Homebrew-alist",
		"url" : "/article/16726547033"
	}
	
	,
	
    
	{
		"title" : "《Alist安卓手机的配置》　2022/12/24　Alist-安卓-termux-清华-MxPlayer-android",
		"url" : "/article/16718726252"
	}
	
	,
	
    
	{
		"title" : "《GitHub Actions》　2022/11/12　GitHub-Action-Yaml-workflow-secrets",
		"url" : "/article/16682372627"
	}
	
	,
	
    
	{
		"title" : "《如何编写无法维护的代码》　2022/10/07　开发-娱乐-代码-维护-原则",
		"url" : "/article/16651247353"
	}
	
	,
	
    
	{
		"title" : "《关闭谷歌浏览器更新 Mac》　2022/09/03　Chrome-更新-浏览器-Google-自动升级",
		"url" : "/article/16621400624"
	}
	
	,
	
    
	{
		"title" : "《研发说这个需求实现不了，为什么？》　2022/08/21　研发-产品经理-技术-成本-需求",
		"url" : "/article/16610720911"
	}
	
	,
	
    
	{
		"title" : "《B站“崩溃”始末》　2022/07/14　服务器-nginx-B站-崩溃-运维",
		"url" : "/article/16577323953"
	}
	
	,
	
    
	{
		"title" : "《MacOS实战：时光本 - 笔记工具》　2022/06/03　个人博客-时光本-小程序-gorpeln-笔记-便签-清单-图片-纪念日-地址-链接-银行卡-名片-待办-日程-高效",
		"url" : "/article/16542416251"
	}
	
	,
	
    
	{
		"title" : "《MacOS：NSMenu》　2022/05/04　NSMenu-NSMenuItem-NSApp-DockMenu",
		"url" : "/article/16516610954"
	}
	
	,
	
    
	{
		"title" : "《MacOS：NSButton》　2022/05/02　NSButton-NSImageOnly-setAction-NSButtonConvenience",
		"url" : "/article/16514594954"
	}
	
	,
	
    
	{
		"title" : "《MacOS：NSWindow、NSWindowController、NSViewController、NSView 的关系和创建》　2022/04/05　NSWindow-NSWindowController-NSViewController-NSView",
		"url" : "/article/16491590954"
	}
	
	,
	
    
	{
		"title" : "《MacOS：使用代码重启应用》　2022/04/03　relaunch-NSWorkspace-NSWorkspaceLaunchAsync-terminate",
		"url" : "/article/16489862954"
	}
	
	,
	
    
	{
		"title" : "《MacOS：鼠标事件》　2022/04/03　鼠标-mouse-mouseDown-NSResponder-NSEvent",
		"url" : "/article/16489790954"
	}
	
	,
	
    
	{
		"title" : "《MacOS：NSTableView》　2022/04/03　NSTableView-dataSource-delegate-Colume-cell",
		"url" : "/article/16489168044"
	}
	
	,
	
    
	{
		"title" : "《获取iOS应用的ipa安装包》　2022/02/05　iOS-APP-ipa-安装包-Configurator",
		"url" : "/article/16440529320"
	}
	
	,
	
    
	{
		"title" : "《网易云音乐听歌300快速10级》　2022/01/01　网易云音乐-听歌-等级-福利-教程",
		"url" : "/article/16410066714"
	}
	
	,
	
    
	{
		"title" : "《​个人技术博客如何选择？（CSDN、博客园、简书、知乎专栏、Github Page）》　2021/06/13　博客-CSDN-博客园-知乎-简书-Github",
		"url" : "/article/16235525192"
	}
	
	,
	
    
	{
		"title" : "《​数字人民币双离线支付实现原理》　2021/05/05　数字人民币-支付-微信-支付宝-离线",
		"url" : "/article/16202019892"
	}
	
	,
	
    
	{
		"title" : "《SDWebImage实现原理》　2021/05/02　SDWebImage-UIImageView-SDImageCache-SDWebImageManager-图片",
		"url" : "/article/16199142732"
	}
	
	,
	
    
	{
		"title" : "《微信小程序（组件 - 自定义组件）》　2021/04/04　手势-优先级-响应链-Delegate",
		"url" : "/article/16175510629"
	}
	
	,
	
    
	{
		"title" : "《微信小程序（事件对象 - 绑定、冒泡、捕获）》　2021/03/27　手势-优先级-响应链-Delegate",
		"url" : "/article/16168523139"
	}
	
	,
	
    
	{
		"title" : "《手势冲突》　2021/02/14　手势-优先级-响应链-Delegate",
		"url" : "/article/16132790510"
	}
	
	,
	
    
	{
		"title" : "《JS与OC交互》　2021/02/13　UIWebView-WKWebView-WebViewJavascriptBridge-JSContext",
		"url" : "/article/16131808742"
	}
	
	,
	
    
	{
		"title" : "《微信小程序使用Promise异步回调,以及使用简单递归算法》　2021/01/03　微信小程序-分享-异步-递归",
		"url" : "/article/16096373020"
	}
	
	,
	
    
	{
		"title" : "《常见排序算法》　2020/12/25　排序-算法-冒泡-选择排序-插入-希尔",
		"url" : "/article/16088892195"
	}
	
	,
	
    
	{
		"title" : "《应用内环境切换》　2020/11/03　测试-预发-正式-灰度-安装包",
		"url" : "/article/16043955947"
	}
	
	,
	
    
	{
		"title" : "《微信小程序（Flex布局-容器属性）》　2020/10/03　微信小程序-Flex布局-容器",
		"url" : "/article/16017022152"
	}
	
	,
	
    
	{
		"title" : "《个性化UI在金融场景的探索和应用》　2020/09/20　UI-支付宝-金融-理财-信用-归因分析",
		"url" : "/article/16005868715"
	}
	
	,
	
    
	{
		"title" : "《本机号码一键登录》　2020/08/30　一键登录-手机号-本机号码-联通-移动-电信",
		"url" : "/article/15987505965"
	}
	
	,
	
    
	{
		"title" : "《5周年：岁月使然而我在等你》　2020/08/23　个人博客-5周年-简洁-高效",
		"url" : "/article/15981552003"
	}
	
	,
	
    
	{
		"title" : "《常见问题 - 时光本》　2020/07/12　时光本-便签-清单-图片-纪念日-地址-链接-银行卡-名片-常见问题",
		"url" : "/article/15945227879"
	}
	
	,
	
    
	{
		"title" : "《如果打开iCloud同步 - 时光本》　2020/07/09　iCloud-时光本-便签-清单-图片-纪念日-地址-链接-银行卡-名片",
		"url" : "/article/15942881574"
	}
	
	,
	
    
	{
		"title" : "《为什么现在很多平台都要手机号注册？》　2020/07/03　手机号-实名制-注册-安全性-运营",
		"url" : "/article/15937625033"
	}
	
	,
	
    
	{
		"title" : "《开发环境、测试环境、预发布环境、生产环境的区别》　2020/06/27　开发环境-测试环境-预发布环境-生产环境-回归环境",
		"url" : "/article/15932337513"
	}
	
	,
	
    
	{
		"title" : "《iOS多线程：线程安全 常见锁 (六)》　2020/06/26　GCD-多线程-常见锁-synchronized-互斥锁-dispatch_semaphore-NSLock-对象锁-NSRecursiveLock-递归锁-NSConditionLock-条件锁-NSCondition-pthread_mutex-OSSpinLock",
		"url" : "/article/15931534585"
	}
	
	,
	
    
	{
		"title" : "《iOS多线程：NSOperation、NSOperationQueue (五)》　2020/05/02　NSOperation-多线程-NSOperationQueue-NSBlockOperation-队列",
		"url" : "/article/15884027619"
	}
	
	,
	
    
	{
		"title" : "《iOS多线程：GCD的实际使用 (四)》　2020/04/07　GCD-多线程-dispatch_async-dispatch_after-dispatch_once-dispatch_group-dispatch_barrier_async-dispatch_apply-dispatch_suspend",
		"url" : "/article/15862323579"
	}
	
	,
	
    
	{
		"title" : "《iOS多线程：GCD (三)》　2020/04/06　GCD-多线程-Dispatch-Queue-dispatch_async-异步执行",
		"url" : "/article/15861494710"
	}
	
	,
	
    
	{
		"title" : "《iOS多线程：NSThread (二)》　2020/04/05　NSThread-多线程-线程-mainThread-currentThread-线程安全",
		"url" : "/article/15860813363"
	}
	
	,
	
    
	{
		"title" : "《iOS多线程：基础 (一)》　2020/03/29　GCD-多线程-进程-任务-队列",
		"url" : "/article/15854795957"
	}
	
	,
	
    
	{
		"title" : "《北京国贸,600块群租房里的24个女孩》　2020/03/20　程序人生-北漂-群租房-蚁居-大学生-毕业生",
		"url" : "/article/15846874151"
	}
	
	,
	
    
	{
		"title" : "《优惠券设计思路浅析》　2020/02/20　优惠券-满减券-代金券-折扣券-通用券-单品券-品类券-店铺券-包邮券",
		"url" : "/article/15821713417"
	}
	
	,
	
    
	{
		"title" : "《关于 ASO 优化（一）》　2020/02/01　App Store-app 推广-精品推荐-排行榜-ASO-留存量-用户量-激活量",
		"url" : "/article/15805392787"
	}
	
	,
	
    
	{
		"title" : "《iOS 微信打开第三方应用（Universal Links 和 URL Schemes）》　2020/01/12　微信-Universal Links-URL Schemes-第三方应用-通用链接-微信",
		"url" : "/article/15788283058"
	}
	
	,
	
    
	{
		"title" : "《临时邮箱 和 短信接码平台》　2020/01/10　临时邮箱-短信-手机号",
		"url" : "/article/15786589400"
	}
	
	,
	
    
	{
		"title" : "《24张一丝不挂的人性照片，值得你看一看》　2020/01/01　程序人生-开心一刻-段子-人性",
		"url" : "/article/15778684175"
	}
	
	,
	
    
	{
		"title" : "《个人项目 - gorpeln》　2019/12/29　个人博客-时光本-小程序-gorpeln-笔记-便签-清单-图片-纪念日-地址-链接-银行卡-名片-待办-日程-高效",
		"url" : "/article/15776115840"
	}
	
	,
	
    
	{
		"title" : "《开心一刻（一）》　2019/11/10　程序人生-开心一刻-段子-暖男-初恋",
		"url" : "/article/15733745781"
	}
	
	,
	
    
	{
		"title" : "《我的Mac软件 备忘》　2019/10/18　Software MAC-Licecap-DaisyDisk-Cyberduck-MWeb-Sublime-Charles-Postman-CleanMymac-BreakTime",
		"url" : "/article/15713829999"
	}
	
	,
	
    
	{
		"title" : "《App Store 审核指南》　2019/10/18　苹果审核-AppStore-开发-隐私",
		"url" : "/article/15713825459"
	}
	
	,
	
    
	{
		"title" : "《锚点跳转距离顶部指定距离》　2019/10/03　锚点-html-scrollTop-onhashchange",
		"url" : "/article/15700906142"
	}
	
	,
	
    
	{
		"title" : "《博客文章 - 简单加密》　2019/09/23　个人博客-加密-password-保密",
		"url" : "/article/15692409843"
	}
	
	,
	
    
	{
		"title" : "《返回并刷新上一个页面》　2019/08/22　微信小程序-loadData-currentPage-onLoad",
		"url" : "/article/15664680297"
	}
	
	,
	
    
	{
		"title" : "《七牛云上传图片 - 客户端》　2019/08/19　七牛云-上传-QiniuSDK-uploadOption",
		"url" : "/article/15662012632"
	}
	
	,
	
    
	{
		"title" : "《文章置顶功能的实现 - Jekyll x Liquid》　2019/07/15　个人博客-Jekyll-文章置顶-endfor",
		"url" : "/article/15632033519"
	}
	
	,
	
    
	{
		"title" : "《扩展篇 ：开发框架及前景》　2019/07/06　微信小程序-WePY-mpvue-前景",
		"url" : "/article/15623480718"
	}
	
	,
	
    
	{
		"title" : "《实战篇 ：电商小程序云开发实战》　2019/06/30　微信小程序-电商-在线预约-购物车-商品详情",
		"url" : "/article/15618778699"
	}
	
	,
	
    
	{
		"title" : "《基础篇 3：小程序架构及其实现机制》　2019/06/23　微信小程序-HTML5-生命周期-数据驱动",
		"url" : "/article/15612663893"
	}
	
	,
	
    
	{
		"title" : "《基础篇 2：小程序·云开发基础知识》　2019/06/22　微信小程序-云开发-数据库-云函数-存储-API调用-request-cloud-database",
		"url" : "/article/15611722666"
	}
	
	,
	
    
	{
		"title" : "《基础篇 1：小程序开发基础知识》　2019/06/15　微信小程序-IDE-Sublime-JavaScript-flex-rpx-路由跳转",
		"url" : "/article/15605697133"
	}
	
	,
	
    
	{
		"title" : "《概述 ：微信小程序概述》　2019/06/08　微信小程序-HTML5-APP-开发账号",
		"url" : "/article/15599710733"
	}
	
	,
	
    
	{
		"title" : "《编程到底难在哪里？》　2019/05/27　程序人生-开心一刻-段子-苹果",
		"url" : "/article/15589479418"
	}
	
	,
	
    
	{
		"title" : "《好玩的H5小游戏·圈小猫~》　2019/05/20　项目-圈小猫-游戏-小游戏",
		"url" : "/article/15583474979"
	}
	
	,
	
    
	{
		"title" : "《微信红包算法》　2019/05/11　抽奖-算法-红包-微信红包",
		"url" : "/article/15575387722"
	}
	
	,
	
    
	{
		"title" : "《抽奖 - 算法》　2019/05/09　抽奖-算法-中奖-随机抽取",
		"url" : "/article/15573877312"
	}
	
	,
	
    
	{
		"title" : "《WOW.js – 有趣的页面滚动效果》　2019/04/11　WOW-动画-animate-动画-duration-animateClass",
		"url" : "/article/15549830140"
	}
	
	,
	
    
	{
		"title" : "《批量修改文件后缀名》　2019/04/08　后缀名-终端-批量修改-chmod",
		"url" : "/article/15547100706"
	}
	
	,
	
    
	{
		"title" : "《iOS App 签名的原理》　2019/03/15　签名机制-App-Profile-AppStore-私钥-非对称加密",
		"url" : "/article/15526269575"
	}
	
	,
	
    
	{
		"title" : "《移动 APP 网络优化概述》　2019/03/13　网络优化-AFNetworking-DNS解析-keep-alive",
		"url" : "/article/15524857215"
	}
	
	,
	
    
	{
		"title" : "《如何访问并修改一个类的私有属性？》　2019/03/03　私有属性-runtime-KVC-msg_send",
		"url" : "/article/15515973239"
	}
	
	,
	
    
	{
		"title" : "《Sublime Text 3安装使用 MAC》　2019/02/14　Sublime Text3-安装使用-代码高亮-Eclipse-Coding-package control",
		"url" : "/article/15501213244"
	}
	
	,
	
    
	{
		"title" : "《神级注释》　2019/02/13　程序人生-注释",
		"url" : "/article/15500354146"
	}
	
	,
	
    
	{
		"title" : "《终端上成功提交了代码，GitHub上Contributions没有变绿》　2019/02/07　GitHub-Git-Contributions-Issues-Commits-Github帐号",
		"url" : "/article/15495225362"
	}
	
	,
	
    
	{
		"title" : "《史上最污技术解读，我竟然秒懂了！》　2019/02/05　程序人生-开心一刻-段子-云备份-热备份-NAS-负载均衡",
		"url" : "/article/15493658365"
	}
	
	,
	
    
	{
		"title" : "《App瘦身、性能优化总结》　2019/01/14　App瘦身-性能优化-Realm-重复代码-逃逸闭包-离屏渲染-TableView",
		"url" : "/article/15474431442"
	}
	
	,
	
    
	{
		"title" : "《博客成长记录...》　2019/01/01　个人博客-博客成长-友链-分类-标签",
		"url" : "/article/15462756619"
	}
	
	,
	
    
	{
		"title" : "《查看QQ下载的视频路径 MAC》　2018/12/03　QQ-视频路径-Software-mac-Library-Videos-com.tencent.qq",
		"url" : "/article/15438182232"
	}
	
	,
	
    
	{
		"title" : "《云开发 与 WePY》　2018/11/23　微信小程序-云开发-WePY-Vue-云开发-MPVue",
		"url" : "/article/15429884147"
	}
	
	,
	
    
	{
		"title" : "《电脑病毒竟然被当宠物养！》　2018/11/14　程序人生-开心一刻-段子-电脑病毒-Steam-宠物",
		"url" : "/article/15421638259"
	}
	
	,
	
    
	{
		"title" : "《Jekyll博客添加GitTalk评论》　2018/11/11　Jekyll-GitTalk-个人博客-博客-GitHub-Client-评论-issue",
		"url" : "/article/15419058710"
	}
	
	,
	
    
	{
		"title" : "《Git管理多个远程仓库（GitHub和Coding）》　2018/10/26　GitHub-Git-Coding-远程仓库-分支-master-本地仓库",
		"url" : "/article/15405204060"
	}
	
	,
	
    
	{
		"title" : "《GitHub 提交次数过多 .git 文件过大的问题》　2018/10/13　GitHub-Git-clone-.git-commit-抛弃部分历史-shallow",
		"url" : "/article/15394160033"
	}
	
	,
	
    
	{
		"title" : "《GitHub回退历史版本》　2018/10/12　Git-GitHub-历史版本-回退-pull-origin",
		"url" : "/article/15393512853"
	}
	
	,
	
    
	{
		"title" : "《微信小程序：回退到首页》　2018/10/08　微信小程序-navigateTo-redirectTo-switchTab-redirectTo-reLaunch",
		"url" : "/article/15389885669"
	}
	
	,
	
    
	{
		"title" : "《Automator的使用 MAC》　2018/10/03　Automator-机器人-自动化-照片大小-重命名-macOS",
		"url" : "/article/15385436862"
	}
	
	,
	
    
	{
		"title" : "《云调用 - 生成小程序码》　2018/09/13　微信小程序-云函数-node.js-npm-wx-server-sdk",
		"url" : "/article/15368306590"
	}
	
	,
	
    
	{
		"title" : "《让你瞬间理解HTTP状态码》　2018/09/06　程序人生-开心一刻-段子-HTTP-状态码-404",
		"url" : "/article/15361983047"
	}
	
	,
	
    
	{
		"title" : "《终端制作带密码的压缩包 Mac》　2018/09/03　zip-终端-MAC-压缩包-密码",
		"url" : "/article/15359479766"
	}
	
	,
	
    
	{
		"title" : "《Github上的代码添加Cocoapods支持》　2018/08/05　Github-Cocoapods-LICENSE-Commit-release-版本",
		"url" : "/article/15334663054"
	}
	
	,
	
    
	{
		"title" : "《触发KVO的修改变量值方法》　2018/07/27　KVO-Observer-通知-监听-setValue",
		"url" : "/article/15326844122"
	}
	
	,
	
    
	{
		"title" : "《KVO用法总结》　2018/07/27　KVO-Observer-通知-监听-setValue",
		"url" : "/article/15326844120"
	}
	
	,
	
    
	{
		"title" : "《tomcat启动和关闭 MAC》　2018/07/25　tomcat-startup-shutdown",
		"url" : "/article/15324985037"
	}
	
	,
	
    
	{
		"title" : "《别再问“在吗”，好吗？》　2018/06/13　程序人生-在吗-沟通效率-套路-开心一刻",
		"url" : "/article/15288656748"
	}
	
	,
	
    
	{
		"title" : "《别问我，在吗？在吗？在吗？程序员眼中得TCP》　2018/06/13　TCP-程序人生-在吗-三次握手-UDP-服务器",
		"url" : "/article/15288536422"
	}
	
	,
	
    
	{
		"title" : "《编程十里，不如你》　2018/05/13　程序人生-开心一刻-段子-编程",
		"url" : "/article/15261978139"
	}
	
	,
	
    
	{
		"title" : "《Github pages个人域名添加SSL》　2018/04/04　个人博客-SSL-域名-证书-DV型-百度云",
		"url" : "/article/15228363519"
	}
	
	,
	
    
	{
		"title" : "《架构师说》　2018/04/02　程序人生-开心一刻-段子-出师表-架构师",
		"url" : "/article/15226027614"
	}
	
	,
	
    
	{
		"title" : "《扫码登录实现原理》　2018/03/21　扫码-登录-二维码-token-redis-网页登录",
		"url" : "/article/15215990385"
	}
	
	,
	
    
	{
		"title" : "《UITextView 的使用》　2018/03/13　UITextView-字数统计-delegate-动态高度-内边距",
		"url" : "/article/15209452183"
	}
	
	,
	
    
	{
		"title" : "《短信验证码防刷机制》　2018/03/08　验证码-时间-手机号-Token-图形验证-Cookie",
		"url" : "/article/15204862561"
	}
	
	,
	
    
	{
		"title" : "《Chrome插件》　2018/02/05　Chrome-插件-Adblock-QRcode-Chrono-Fatkun-Infinity-Linkclump",
		"url" : "/article/15178011950"
	}
	
	,
	
    
	{
		"title" : "《Jekyll 使用》　2018/01/23　个人博客-Jekyll-build-_config-_drafts",
		"url" : "/article/15166860457"
	}
	
	,
	
    
	{
		"title" : "《编程就像两性关系》　2018/01/07　程序人生-开心一刻-段子",
		"url" : "/article/15153005416"
	}
	
	,
	
    
	{
		"title" : "《GCD 应用场景》　2017/12/19　GCD-定时器-线程-延时-耗时操作",
		"url" : "/article/15136989613"
	}
	
	,
	
    
	{
		"title" : "《iOS页面流畅技巧》　2017/11/29　页面流畅-卡顿-CALayer-Autolayout-资源消耗",
		"url" : "/article/15119562214"
	}
	
	,
	
    
	{
		"title" : "《整站下载工具httrack使用 MAC》　2017/11/25　httrack-brew-websites-Mirror",
		"url" : "/article/15115957926"
	}
	
	,
	
    
	{
		"title" : "《PhpStorm2017 激活和汉化 MAC》　2017/10/26　PhpStorm2017-License-汉化-PhpStorm-Activate",
		"url" : "/article/15090326823"
	}
	
	,
	
    
	{
		"title" : "《Mac 常用快捷键》　2017/10/11　Mac-快捷键-预览-退出-教程",
		"url" : "/article/15077042074"
	}
	
	,
	
    
	{
		"title" : "《Mac 使用技巧》　2017/10/10　MAC使用-访达-隐藏文件-截屏应用已经损坏-权限",
		"url" : "/article/15076490854"
	}
	
	,
	
    
	{
		"title" : "《iOS11开发遇到的坑》　2017/09/26　iOS-iOS11-Xcode-available-报错",
		"url" : "/article/15064370822"
	}
	
	,
	
    
	{
		"title" : "《如果代码按行付费，会有什么好玩的事情发生？》　2017/08/23　程序人生-缩行师-程序员-开心一刻-段子",
		"url" : "/article/15034734259"
	}
	
	,
	
    
	{
		"title" : "《一张图告诉大家，为啥胖了气质会垮？》　2017/07/21　程序人生-开心一刻-段子",
		"url" : "/article/15006512926"
	}
	
	,
	
    
	{
		"title" : "《HTML数组的基本操作(增删改查、删除重复元素)》　2017/06/27　HTML-增删改查-代码段-数组-删除元素-unshift-splice-push",
		"url" : "/article/14985344961"
	}
	
	,
	
    
	{
		"title" : "《产品经理频繁更改需求为什么会让程序员烦恼？》　2017/06/13　程序人生-产品-原始需求-点餐-宫保鸡丁",
		"url" : "/article/14973389134"
	}
	
	,
	
    
	{
		"title" : "《App提交苹果审核被拒原因总结(二)》　2017/06/10　APP审核-苹果-App Store-拒绝原因",
		"url" : "/article/14970863549"
	}
	
	,
	
    
	{
		"title" : "《App提交苹果审核被拒原因总结(一)》　2017/06/08　APP审核-苹果-App Store-拒绝原因-登录",
		"url" : "/article/14968977690"
	}
	
	,
	
    
	{
		"title" : "《甲方：你能不能在放大LOGO的同时缩小点？》　2017/05/26　程序人生-开心一刻-段子-LOGO-五彩斑斓的黑-甲方",
		"url" : "/article/14957851016"
	}
	
	,
	
    
	{
		"title" : "《程序员眼中的用户》　2017/04/15　程序人生-开心一刻-段子-程序员-用户-需求-程序",
		"url" : "/article/14922464812"
	}
	
	,
	
    
	{
		"title" : "《解析HTTP协议请求方法GET、HEAD、PUT、DELETE、POST、 OPTIONS》　2017/03/27　HTTP协议-GET-POST-PUT-Delete-HEAD-OPTIONS",
		"url" : "/article/14906012630"
	}
	
	,
	
    
	{
		"title" : "《iOS值传递》　2017/03/24　值传递-代码段-属性传值-NSUserDefaults-delegate-NSNotificationCenter-KVO-blcok",
		"url" : "/article/14903507538"
	}
	
	,
	
    
	{
		"title" : "《present,dismiss到任意控制器(二)》　2017/03/16　present-dismiss-代码段",
		"url" : "/article/14896376367"
	}
	
	,
	
    
	{
		"title" : "《数组操作：倒序、乱序》　2017/02/28　NSArray-倒序-乱序-代码段-排序",
		"url" : "/article/14882587810"
	}
	
	,
	
    
	{
		"title" : "《Label中某几个字符颜色大小不同》　2017/02/20　UIlabel-代码段-颜色-富文本-attributedText",
		"url" : "/article/14875801742"
	}
	
	,
	
    
	{
		"title" : "《开发编码规范建议》　2017/02/17　开发规范-宏定义-layoutSubviews-常量-布局",
		"url" : "/article/14873067700"
	}
	
	,
	
    
	{
		"title" : "《限制UITextField的文字长度》　2017/02/16　UITextField-代码段-UITextFieldDelegate-限制位数-location",
		"url" : "/article/14872573275"
	}
	
	,
	
    
	{
		"title" : "《录制GIF动画 MAC》　2017/02/06　GIF动画-Licecap-gif图片-mac-软件使用",
		"url" : "/article/14863391315"
	}
	
	,
	
    
	{
		"title" : "《字符串的删除替换》　2017/02/04　NSString-代码段-字符串-删除-替换",
		"url" : "/article/14861973259"
	}
	
	,
	
    
	{
		"title" : "《push,pop到任意控制器(一)》　2016/10/28　push-pop-代码段-控制器-跳转",
		"url" : "/article/14776665877"
	}
	
	,
	
    
	{
		"title" : "《设置任意某个角为圆角》　2016/09/20　贝塞尔曲线-代码段-圆角-CAShapeLayer-UIBezierPath",
		"url" : "/article/14743559444"
	}
	
	,
	
    
	{
		"title" : "《冒泡排序》　2016/07/27　冒泡排序-算法-数组-排序",
		"url" : "/article/14696000759"
	}
	
	,
	
    
	{
		"title" : "《为什么不应该加班？》　2016/06/26　程序人生-加班-代码审核-加班的好处-加班的坏处",
		"url" : "/article/14669248561"
	}
	
	,
	
    
	{
		"title" : "《iOS9 HTTP 不能正常使用的解决办法（数据无法加载）》　2015/10/25　Bug调试-iOS9-HTTPS协议-NSAppTransportSecurity-Security",
		"url" : "/article/14457584631"
	}
	
	,
	
    
	{
		"title" : "《You must rebuild it with bitcode enabled (Xcode setting ENABLE_BITCODE)》　2015/10/04　Bug调试-ENABLE_BITCODE-URGENT-调试",
		"url" : "/article/14439563950"
	}
	
	,
	
    
	{
		"title" : "《优化MySQL中的分页》　2015/09/20　MySQL-分页-数据库-ORDERBY-InnoDB",
		"url" : "/article/14427478333"
	}
	
	,
	
    
	{
		"title" : "《web前端规范》　2015/09/01　web规范-开发规范-JAVASCRIPT-OPTGROUP-XHTML标准",
		"url" : "/article/14411221175"
	}
	
	,
	
    
	{
		"title" : "《Linux常用命令总结》　2015/08/25　Linux-mkdir-删除文件-建立目录-文件权限-其他",
		"url" : "/article/14404771043"
	}
	
	,
	
    
	{
		"title" : "《Hello World》　2015/08/23　个人博客-书写笔记-Markdown-纯文本标记语言-链接",
		"url" : "/article/14402966023"
	}
	
	,
	
    
	{
		"title" : "《杂记》　2015/03/30　其他",
		"url" : "/p/30"
	}
	
	,
	
    
	{
		"title" : "《近现代文学作品》　2015/03/28　其他",
		"url" : "/p/28"
	}
	
	,
	
    
	{
		"title" : "《航天、科技》　2015/03/27　其他",
		"url" : "/p/27"
	}
	
	,
	
    
	{
		"title" : "《诸子百家》　2015/03/26　其他",
		"url" : "/p/26"
	}
	
	,
	
    
	{
		"title" : "《电影》　2015/03/25　其他",
		"url" : "/p/25"
	}
	
	,
	
    
	{
		"title" : "《中国的原始社会》　2015/03/24　其他",
		"url" : "/p/24"
	}
	
	,
	
    
	{
		"title" : "《个税法》　2015/03/23　其他",
		"url" : "/p/23"
	}
	
	,
	
    
	{
		"title" : "《行政法》　2015/03/22　其他",
		"url" : "/p/22"
	}
	
	,
	
    
	{
		"title" : "《刑法》　2015/03/21　其他",
		"url" : "/p/21"
	}
	
	,
	
    
	{
		"title" : "《民法》　2015/03/20　其他",
		"url" : "/p/20"
	}
	
	,
	
    
	{
		"title" : "《宪法》　2015/03/19　其他",
		"url" : "/p/19"
	}
	
	,
	
    
	{
		"title" : "《马哲》　2015/03/18　其他",
		"url" : "/p/18"
	}
	
	,
	
    
	{
		"title" : "《中国近现代重要战争》　2015/03/17　其他",
		"url" : "/p/17"
	}
	
	,
	
    
	{
		"title" : "《古代天文历法》　2015/03/16　其他",
		"url" : "/p/16"
	}
	
	,
	
    
	{
		"title" : "《经济》　2015/03/15　其他",
		"url" : "/p/15"
	}
	
	,
	
    
	{
		"title" : "《世界史》　2015/03/14　其他",
		"url" : "/p/14"
	}
	
	,
	
    
	{
		"title" : "《诗词、文曲、小说、音乐》　2015/03/13　其他",
		"url" : "/p/13"
	}
	
	,
	
    
	{
		"title" : "《四大文明古国》　2015/03/12　其他",
		"url" : "/p/12"
	}
	
	,
	
    
	{
		"title" : "《民族节日》　2015/03/11　其他",
		"url" : "/p/11"
	}
	
	,
	
    
	{
		"title" : "《古代建筑》　2015/03/10　其他",
		"url" : "/p/10"
	}
	
	,
	
    
	{
		"title" : "《中医》　2015/03/09　其他",
		"url" : "/p/09"
	}
	
	,
	
    
	{
		"title" : "《书法、绘画》　2015/03/08　其他",
		"url" : "/p/08"
	}
	
	,
	
    
	{
		"title" : "《地理》　2015/03/07　其他",
		"url" : "/p/07"
	}
	
	,
	
    
	{
		"title" : "《王侯将相》　2015/03/06　其他",
		"url" : "/p/06"
	}
	
	,
	
    
	{
		"title" : "《古代制度》　2015/03/05　其他",
		"url" : "/p/05"
	}
	
	,
	
    
	{
		"title" : "《生物、物理、化学、生活》　2015/03/04　其他",
		"url" : "/p/04"
	}
	
	,
	
    
	{
		"title" : "《中国古代重要战争》　2015/03/03　其他",
		"url" : "/p/03"
	}
	
	,
	
    
	{
		"title" : "《国际组织》　2015/03/02　其他",
		"url" : "/p/02"
	}
	
	,
	
    
	{
		"title" : "《党史》　2015/03/01　其他",
		"url" : "/p/01"
	}
	
	,
	
    
	{
		"title" : "《真假推理详解》　2015/02/07　其他",
		"url" : "/b/07"
	}
	
	,
	
    
	{
		"title" : "《成语辨析》　2015/02/06　其他",
		"url" : "/b/06"
	}
	
	,
	
    
	{
		"title" : "《申论》　2015/02/06　其他",
		"url" : "/b/05"
	}
	
	,
	
    
	{
		"title" : "《数量关系》　2015/02/04　其他",
		"url" : "/b/04"
	}
	
	,
	
    
	{
		"title" : "《资料分析》　2015/02/03　其他",
		"url" : "/b/03"
	}
	
	,
	
    
	{
		"title" : "《推理判断》　2015/02/02　其他",
		"url" : "/b/02"
	}
	
	,
	
    
	{
		"title" : "《言语理解与表达》　2015/02/01　其他",
		"url" : "/b/01"
	}
	
	,
	
    
	{
		"title" : "《杂记十》　2015/01/10　其他",
		"url" : "/i/10"
	}
	
	,
	
    
	{
		"title" : "《杂记九》　2015/01/09　其他",
		"url" : "/i/09"
	}
	
	,
	
    
	{
		"title" : "《杂记八》　2015/01/08　其他",
		"url" : "/i/08"
	}
	
	,
	
    
	{
		"title" : "《杂记七》　2015/01/07　其他",
		"url" : "/i/07"
	}
	
	,
	
    
	{
		"title" : "《杂记六》　2015/01/06　其他",
		"url" : "/i/06"
	}
	
	,
	
    
	{
		"title" : "《杂记五》　2015/01/05　其他",
		"url" : "/i/05"
	}
	
	,
	
    
	{
		"title" : "《杂记四》　2015/01/04　其他",
		"url" : "/i/04"
	}
	
	,
	
    
	{
		"title" : "《杂记三》　2015/01/03　其他",
		"url" : "/i/03"
	}
	
	,
	
    
	{
		"title" : "《杂记二》　2015/01/02　其他",
		"url" : "/i/02"
	}
	
	,
	
    
	{
		"title" : "《杂记一》　2015/01/01　其他",
		"url" : "/i/01"
	}
	
	,
	
    
	{
		"title" : "《龙梅子   爱情专属权》　2014/08/14　其他",
		"url" : "/m/%E9%BE%99%E6%A2%85%E5%AD%90-%E7%88%B1%E6%83%85%E4%B8%93%E5%B1%9E%E6%9D%83"
	}
	
	,
	
    
	{
		"title" : "《黎明   全日爱》　2014/08/14　其他",
		"url" : "/m/%E9%BB%8E%E6%98%8E-%E5%85%A8%E6%97%A5%E7%88%B1"
	}
	
	,
	
    
	{
		"title" : "《黄霄雲   星辰大海》　2014/08/14　其他",
		"url" : "/m/%E9%BB%84%E9%9C%84%E9%9B%B2-%E6%98%9F%E8%BE%B0%E5%A4%A7%E6%B5%B7"
	}
	
	,
	
    
	{
		"title" : "《黄勇   男人花》　2014/08/14　其他",
		"url" : "/m/%E9%BB%84%E5%8B%87-%E7%94%B7%E4%BA%BA%E8%8A%B1"
	}
	
	,
	
    
	{
		"title" : "《麦小兜   下山》　2014/08/14　其他",
		"url" : "/m/%E9%BA%A6%E5%B0%8F%E5%85%9C-%E4%B8%8B%E5%B1%B1"
	}
	
	,
	
    
	{
		"title" : "《魏新雨   百花香》　2014/08/14　其他",
		"url" : "/m/%E9%AD%8F%E6%96%B0%E9%9B%A8-%E7%99%BE%E8%8A%B1%E9%A6%99"
	}
	
	,
	
    
	{
		"title" : "《魏新雨   恋人心》　2014/08/14　其他",
		"url" : "/m/%E9%AD%8F%E6%96%B0%E9%9B%A8-%E6%81%8B%E4%BA%BA%E5%BF%83"
	}
	
	,
	
    
	{
		"title" : "《魏新雨   余情未了》　2014/08/14　其他",
		"url" : "/m/%E9%AD%8F%E6%96%B0%E9%9B%A8-%E4%BD%99%E6%83%85%E6%9C%AA%E4%BA%86"
	}
	
	,
	
    
	{
		"title" : "《魏佳艺   孟婆的碗》　2014/08/14　其他",
		"url" : "/m/%E9%AD%8F%E4%BD%B3%E8%89%BA-%E5%AD%9F%E5%A9%86%E7%9A%84%E7%A2%97"
	}
	
	,
	
    
	{
		"title" : "《马雨梵   邂逅》　2014/08/14　其他",
		"url" : "/m/%E9%A9%AC%E9%9B%A8%E6%A2%B5-%E9%82%82%E9%80%85"
	}
	
	,
	
    
	{
		"title" : "《马郁   下辈子如果我还记得你》　2014/08/14　其他",
		"url" : "/m/%E9%A9%AC%E9%83%81-%E4%B8%8B%E8%BE%88%E5%AD%90%E5%A6%82%E6%9E%9C%E6%88%91%E8%BF%98%E8%AE%B0%E5%BE%97%E4%BD%A0"
	}
	
	,
	
    
	{
		"title" : "《香香   哎呦哎呦对不起》　2014/08/14　其他",
		"url" : "/m/%E9%A6%99%E9%A6%99-%E5%93%8E%E5%91%A6%E5%93%8E%E5%91%A6%E5%AF%B9%E4%B8%8D%E8%B5%B7"
	}
	
	,
	
    
	{
		"title" : "《飞轮海,田馥甄   只对你有感觉》　2014/08/14　其他",
		"url" : "/m/%E9%A3%9E%E8%BD%AE%E6%B5%B7,%E7%94%B0%E9%A6%A5%E7%94%84-%E5%8F%AA%E5%AF%B9%E4%BD%A0%E6%9C%89%E6%84%9F%E8%A7%89"
	}
	
	,
	
    
	{
		"title" : "《飞儿乐团   我们的爱》　2014/08/14　其他",
		"url" : "/m/%E9%A3%9E%E5%84%BF%E4%B9%90%E5%9B%A2-%E6%88%91%E4%BB%AC%E7%9A%84%E7%88%B1"
	}
	
	,
	
    
	{
		"title" : "《飞儿乐团   千年之恋》　2014/08/14　其他",
		"url" : "/m/%E9%A3%9E%E5%84%BF%E4%B9%90%E5%9B%A2-%E5%8D%83%E5%B9%B4%E4%B9%8B%E6%81%8B"
	}
	
	,
	
    
	{
		"title" : "《飞儿乐团   你的微笑》　2014/08/14　其他",
		"url" : "/m/%E9%A3%9E%E5%84%BF%E4%B9%90%E5%9B%A2-%E4%BD%A0%E7%9A%84%E5%BE%AE%E7%AC%91"
	}
	
	,
	
    
	{
		"title" : "《飞儿乐团   lydia》　2014/08/14　其他",
		"url" : "/m/%E9%A3%9E%E5%84%BF%E4%B9%90%E5%9B%A2-Lydia"
	}
	
	,
	
    
	{
		"title" : "《风小筝   神度》　2014/08/14　其他",
		"url" : "/m/%E9%A3%8E%E5%B0%8F%E7%AD%9D-%E7%A5%9E%E5%BA%A6"
	}
	
	,
	
    
	{
		"title" : "《音阙诗听 _ 赵方婧   芒种》　2014/08/14　其他",
		"url" : "/m/%E9%9F%B3%E9%98%99%E8%AF%97%E5%90%AC-_-%E8%B5%B5%E6%96%B9%E5%A9%A7-%E8%8A%92%E7%A7%8D"
	}
	
	,
	
    
	{
		"title" : "《音阙诗听 _ 王梓钰   惊蛰》　2014/08/14　其他",
		"url" : "/m/%E9%9F%B3%E9%98%99%E8%AF%97%E5%90%AC-_-%E7%8E%8B%E6%A2%93%E9%92%B0-%E6%83%8A%E8%9B%B0"
	}
	
	,
	
    
	{
		"title" : "《音阙诗听 _ 李佳思   the star》　2014/08/14　其他",
		"url" : "/m/%E9%9F%B3%E9%98%99%E8%AF%97%E5%90%AC-_-%E6%9D%8E%E4%BD%B3%E6%80%9D-The-Star"
	}
	
	,
	
    
	{
		"title" : "《音阙诗听   红昭愿》　2014/08/14　其他",
		"url" : "/m/%E9%9F%B3%E9%98%99%E8%AF%97%E5%90%AC-%E7%BA%A2%E6%98%AD%E6%84%BF"
	}
	
	,
	
    
	{
		"title" : "《音格概念 _ 逸霄   察觉》　2014/08/14　其他",
		"url" : "/m/%E9%9F%B3%E6%A0%BC%E6%A6%82%E5%BF%B5-_-%E9%80%B8%E9%9C%84-%E5%AF%9F%E8%A7%89"
	}
	
	,
	
    
	{
		"title" : "《韩红 林俊杰   飞云之下》　2014/08/14　其他",
		"url" : "/m/%E9%9F%A9%E7%BA%A2-%E6%9E%97%E4%BF%8A%E6%9D%B0-%E9%A3%9E%E4%BA%91%E4%B9%8B%E4%B8%8B"
	}
	
	,
	
    
	{
		"title" : "《鞠文娴   bingbian病变 (女声版)》　2014/08/14　其他",
		"url" : "/m/%E9%9E%A0%E6%96%87%E5%A8%B4-BINGBIAN%E7%97%85%E5%8F%98-(%E5%A5%B3%E5%A3%B0%E7%89%88)"
	}
	
	,
	
    
	{
		"title" : "《青鸟飞鱼   此生不换》　2014/08/14　其他",
		"url" : "/m/%E9%9D%92%E9%B8%9F%E9%A3%9E%E9%B1%BC-%E6%AD%A4%E7%94%9F%E4%B8%8D%E6%8D%A2"
	}
	
	,
	
    
	{
		"title" : "《降央卓玛   走天涯》　2014/08/14　其他",
		"url" : "/m/%E9%99%8D%E5%A4%AE%E5%8D%93%E7%8E%9B-%E8%B5%B0%E5%A4%A9%E6%B6%AF"
	}
	
	,
	
    
	{
		"title" : "《降央卓玛   西海情歌》　2014/08/14　其他",
		"url" : "/m/%E9%99%8D%E5%A4%AE%E5%8D%93%E7%8E%9B-%E8%A5%BF%E6%B5%B7%E6%83%85%E6%AD%8C"
	}
	
	,
	
    
	{
		"title" : "《陈雪凝   绿色》　2014/08/14　其他",
		"url" : "/m/%E9%99%88%E9%9B%AA%E5%87%9D-%E7%BB%BF%E8%89%B2"
	}
	
	,
	
    
	{
		"title" : "《陈雪凝   白山茶》　2014/08/14　其他",
		"url" : "/m/%E9%99%88%E9%9B%AA%E5%87%9D-%E7%99%BD%E5%B1%B1%E8%8C%B6"
	}
	
	,
	
    
	{
		"title" : "《陈雪凝   你的酒馆对我打了烊》　2014/08/14　其他",
		"url" : "/m/%E9%99%88%E9%9B%AA%E5%87%9D-%E4%BD%A0%E7%9A%84%E9%85%92%E9%A6%86%E5%AF%B9%E6%88%91%E6%89%93%E4%BA%86%E7%83%8A"
	}
	
	,
	
    
	{
		"title" : "《陈雅森   下辈子不一定还能遇见你》　2014/08/14　其他",
		"url" : "/m/%E9%99%88%E9%9B%85%E6%A3%AE-%E4%B8%8B%E8%BE%88%E5%AD%90%E4%B8%8D%E4%B8%80%E5%AE%9A%E8%BF%98%E8%83%BD%E9%81%87%E8%A7%81%E4%BD%A0"
	}
	
	,
	
    
	{
		"title" : "《陈粒   走马》　2014/08/14　其他",
		"url" : "/m/%E9%99%88%E7%B2%92-%E8%B5%B0%E9%A9%AC"
	}
	
	,
	
    
	{
		"title" : "《陈粒   虚拟》　2014/08/14　其他",
		"url" : "/m/%E9%99%88%E7%B2%92-%E8%99%9A%E6%8B%9F"
	}
	
	,
	
    
	{
		"title" : "《陈粒   易燃易爆炸》　2014/08/14　其他",
		"url" : "/m/%E9%99%88%E7%B2%92-%E6%98%93%E7%87%83%E6%98%93%E7%88%86%E7%82%B8"
	}
	
	,
	
    
	{
		"title" : "《陈粒   戏台》　2014/08/14　其他",
		"url" : "/m/%E9%99%88%E7%B2%92-%E6%88%8F%E5%8F%B0"
	}
	
	,
	
    
	{
		"title" : "《陈粒   小半》　2014/08/14　其他",
		"url" : "/m/%E9%99%88%E7%B2%92-%E5%B0%8F%E5%8D%8A"
	}
	
	,
	
    
	{
		"title" : "《陈瑞   白狐》　2014/08/14　其他",
		"url" : "/m/%E9%99%88%E7%91%9E-%E7%99%BD%E7%8B%90"
	}
	
	,
	
    
	{
		"title" : "《陈明   我要找到你》　2014/08/14　其他",
		"url" : "/m/%E9%99%88%E6%98%8E-%E6%88%91%E8%A6%81%E6%89%BE%E5%88%B0%E4%BD%A0"
	}
	
	,
	
    
	{
		"title" : "《陈慧琳   都是你的错》　2014/08/14　其他",
		"url" : "/m/%E9%99%88%E6%85%A7%E7%90%B3-%E9%83%BD%E6%98%AF%E4%BD%A0%E7%9A%84%E9%94%99"
	}
	
	,
	
    
	{
		"title" : "《陈慧琳   记事本》　2014/08/14　其他",
		"url" : "/m/%E9%99%88%E6%85%A7%E7%90%B3-%E8%AE%B0%E4%BA%8B%E6%9C%AC"
	}
	
	,
	
    
	{
		"title" : "《陈奕迅   爱情转移》　2014/08/14　其他",
		"url" : "/m/%E9%99%88%E5%A5%95%E8%BF%85-%E7%88%B1%E6%83%85%E8%BD%AC%E7%A7%BB"
	}
	
	,
	
    
	{
		"title" : "《陈奕迅   富士山下》　2014/08/14　其他",
		"url" : "/m/%E9%99%88%E5%A5%95%E8%BF%85-%E5%AF%8C%E5%A3%AB%E5%B1%B1%E4%B8%8B"
	}
	
	,
	
    
	{
		"title" : "《陈奕迅   十年》　2014/08/14　其他",
		"url" : "/m/%E9%99%88%E5%A5%95%E8%BF%85-%E5%8D%81%E5%B9%B4"
	}
	
	,
	
    
	{
		"title" : "《陈一发儿   童话镇》　2014/08/14　其他",
		"url" : "/m/%E9%99%88%E4%B8%80%E5%8F%91%E5%84%BF-%E7%AB%A5%E8%AF%9D%E9%95%87"
	}
	
	,
	
    
	{
		"title" : "《阿里郎   隔壁泰山》　2014/08/14　其他",
		"url" : "/m/%E9%98%BF%E9%87%8C%E9%83%8E-%E9%9A%94%E5%A3%81%E6%B3%B0%E5%B1%B1"
	}
	
	,
	
    
	{
		"title" : "《阿里郎   兰花指》　2014/08/14　其他",
		"url" : "/m/%E9%98%BF%E9%87%8C%E9%83%8E-%E5%85%B0%E8%8A%B1%E6%8C%87"
	}
	
	,
	
    
	{
		"title" : "《阿肆   喜欢》　2014/08/14　其他",
		"url" : "/m/%E9%98%BF%E8%82%86-%E5%96%9C%E6%AC%A2"
	}
	
	,
	
    
	{
		"title" : "《阿梨粤   秒针》　2014/08/14　其他",
		"url" : "/m/%E9%98%BF%E6%A2%A8%E7%B2%A4-%E7%A7%92%E9%92%88"
	}
	
	,
	
    
	{
		"title" : "《阿悠悠   旧梦一场》　2014/08/14　其他",
		"url" : "/m/%E9%98%BF%E6%82%A0%E6%82%A0-%E6%97%A7%E6%A2%A6%E4%B8%80%E5%9C%BA"
	}
	
	,
	
    
	{
		"title" : "《阿悠悠   念旧》　2014/08/14　其他",
		"url" : "/m/%E9%98%BF%E6%82%A0%E6%82%A0-%E5%BF%B5%E6%97%A7"
	}
	
	,
	
    
	{
		"title" : "《阿悠悠   你若三冬》　2014/08/14　其他",
		"url" : "/m/%E9%98%BF%E6%82%A0%E6%82%A0-%E4%BD%A0%E8%8B%A5%E4%B8%89%E5%86%AC"
	}
	
	,
	
    
	{
		"title" : "《阿吉太组合   阿衣莫》　2014/08/14　其他",
		"url" : "/m/%E9%98%BF%E5%90%89%E5%A4%AA%E7%BB%84%E5%90%88-%E9%98%BF%E8%A1%A3%E8%8E%AB"
	}
	
	,
	
    
	{
		"title" : "《阿冗   你的答案》　2014/08/14　其他",
		"url" : "/m/%E9%98%BF%E5%86%97-%E4%BD%A0%E7%9A%84%E7%AD%94%E6%A1%88"
	}
	
	,
	
    
	{
		"title" : "《阿兰、胡歌   一念执着》　2014/08/14　其他",
		"url" : "/m/%E9%98%BF%E5%85%B0-%E8%83%A1%E6%AD%8C-%E4%B8%80%E5%BF%B5%E6%89%A7%E7%9D%80"
	}
	
	,
	
    
	{
		"title" : "《阿yueyue   云与海》　2014/08/14　其他",
		"url" : "/m/%E9%98%BFYueYue-%E4%BA%91%E4%B8%8E%E6%B5%B7"
	}
	
	,
	
    
	{
		"title" : "《闻人听書_   虞兮叹（dj沈念）》　2014/08/14　其他",
		"url" : "/m/%E9%97%BB%E4%BA%BA%E5%90%AC%E6%9B%B8_-%E8%99%9E%E5%85%AE%E5%8F%B9-DJ%E6%B2%88%E5%BF%B5"
	}
	
	,
	
    
	{
		"title" : "《闻人听書_   虞兮叹》　2014/08/14　其他",
		"url" : "/m/%E9%97%BB%E4%BA%BA%E5%90%AC%E6%9B%B8_-%E8%99%9E%E5%85%AE%E5%8F%B9"
	}
	
	,
	
    
	{
		"title" : "《闻人听書_   美人画卷》　2014/08/14　其他",
		"url" : "/m/%E9%97%BB%E4%BA%BA%E5%90%AC%E6%9B%B8_-%E7%BE%8E%E4%BA%BA%E7%94%BB%E5%8D%B7"
	}
	
	,
	
    
	{
		"title" : "《闻人听書_   美人画卷 (dj沈念版)》　2014/08/14　其他",
		"url" : "/m/%E9%97%BB%E4%BA%BA%E5%90%AC%E6%9B%B8_-%E7%BE%8E%E4%BA%BA%E7%94%BB%E5%8D%B7-(DJ%E6%B2%88%E5%BF%B5%E7%89%88)"
	}
	
	,
	
    
	{
		"title" : "《锦零   恋爱画板》　2014/08/14　其他",
		"url" : "/m/%E9%94%A6%E9%9B%B6-%E6%81%8B%E7%88%B1%E7%94%BB%E6%9D%BF"
	}
	
	,
	
    
	{
		"title" : "《金池   谁不是》　2014/08/14　其他",
		"url" : "/m/%E9%87%91%E6%B1%A0-%E8%B0%81%E4%B8%8D%E6%98%AF"
	}
	
	,
	
    
	{
		"title" : "《金志文   远走高飞》　2014/08/14　其他",
		"url" : "/m/%E9%87%91%E5%BF%97%E6%96%87-%E8%BF%9C%E8%B5%B0%E9%AB%98%E9%A3%9E"
	}
	
	,
	
    
	{
		"title" : "《金南玲 _ 李俊佑   超级喜欢你》　2014/08/14　其他",
		"url" : "/m/%E9%87%91%E5%8D%97%E7%8E%B2-_-%E6%9D%8E%E4%BF%8A%E4%BD%91-%E8%B6%85%E7%BA%A7%E5%96%9C%E6%AC%A2%E4%BD%A0"
	}
	
	,
	
    
	{
		"title" : "《郭静   心墙》　2014/08/14　其他",
		"url" : "/m/%E9%83%AD%E9%9D%99-%E5%BF%83%E5%A2%99"
	}
	
	,
	
    
	{
		"title" : "《郭静   在树上唱歌》　2014/08/14　其他",
		"url" : "/m/%E9%83%AD%E9%9D%99-%E5%9C%A8%E6%A0%91%E4%B8%8A%E5%94%B1%E6%AD%8C"
	}
	
	,
	
    
	{
		"title" : "《郭静   你的香气》　2014/08/14　其他",
		"url" : "/m/%E9%83%AD%E9%9D%99-%E4%BD%A0%E7%9A%84%E9%A6%99%E6%B0%94"
	}
	
	,
	
    
	{
		"title" : "《郭静   下一个天亮》　2014/08/14　其他",
		"url" : "/m/%E9%83%AD%E9%9D%99-%E4%B8%8B%E4%B8%80%E4%B8%AA%E5%A4%A9%E4%BA%AE"
	}
	
	,
	
    
	{
		"title" : "《郑源   我不后悔》　2014/08/14　其他",
		"url" : "/m/%E9%83%91%E6%BA%90-%E6%88%91%E4%B8%8D%E5%90%8E%E6%82%94"
	}
	
	,
	
    
	{
		"title" : "《郑伊健   热血燃烧》　2014/08/14　其他",
		"url" : "/m/%E9%83%91%E4%BC%8A%E5%81%A5-%E7%83%AD%E8%A1%80%E7%87%83%E7%83%A7"
	}
	
	,
	
    
	{
		"title" : "《郁可唯   你曾说》　2014/08/14　其他",
		"url" : "/m/%E9%83%81%E5%8F%AF%E5%94%AF-%E4%BD%A0%E6%9B%BE%E8%AF%B4"
	}
	
	,
	
    
	{
		"title" : "《邰正宵   千纸鹤》　2014/08/14　其他",
		"url" : "/m/%E9%82%B0%E6%AD%A3%E5%AE%B5-%E5%8D%83%E7%BA%B8%E9%B9%A4"
	}
	
	,
	
    
	{
		"title" : "《邰正宵   九百九十九朵玫瑰》　2014/08/14　其他",
		"url" : "/m/%E9%82%B0%E6%AD%A3%E5%AE%B5-%E4%B9%9D%E7%99%BE%E4%B9%9D%E5%8D%81%E4%B9%9D%E6%9C%B5%E7%8E%AB%E7%91%B0"
	}
	
	,
	
    
	{
		"title" : "《赵钶   有人》　2014/08/14　其他",
		"url" : "/m/%E8%B5%B5%E9%92%B6-%E6%9C%89%E4%BA%BA"
	}
	
	,
	
    
	{
		"title" : "《赵芷彤   甜甜咸咸》　2014/08/14　其他",
		"url" : "/m/%E8%B5%B5%E8%8A%B7%E5%BD%A4-%E7%94%9C%E7%94%9C%E5%92%B8%E5%92%B8"
	}
	
	,
	
    
	{
		"title" : "《赵洋   抽烟伤肺喝酒伤胃》　2014/08/14　其他",
		"url" : "/m/%E8%B5%B5%E6%B4%8B-%E6%8A%BD%E7%83%9F%E4%BC%A4%E8%82%BA%E5%96%9D%E9%85%92%E4%BC%A4%E8%83%83"
	}
	
	,
	
    
	{
		"title" : "《赵方婧 _ 音阙诗听   离人殇》　2014/08/14　其他",
		"url" : "/m/%E8%B5%B5%E6%96%B9%E5%A9%A7-_-%E9%9F%B3%E9%98%99%E8%AF%97%E5%90%AC-%E7%A6%BB%E4%BA%BA%E6%AE%87"
	}
	
	,
	
    
	{
		"title" : "《赵方婧   尽头》　2014/08/14　其他",
		"url" : "/m/%E8%B5%B5%E6%96%B9%E5%A9%A7-%E5%B0%BD%E5%A4%B4"
	}
	
	,
	
    
	{
		"title" : "《赵乃吉   曾经你说》　2014/08/14　其他",
		"url" : "/m/%E8%B5%B5%E4%B9%83%E5%90%89-%E6%9B%BE%E7%BB%8F%E4%BD%A0%E8%AF%B4"
	}
	
	,
	
    
	{
		"title" : "《贺敬轩   罗曼蒂克的爱情》　2014/08/14　其他",
		"url" : "/m/%E8%B4%BA%E6%95%AC%E8%BD%A9-%E7%BD%97%E6%9B%BC%E8%92%82%E5%85%8B%E7%9A%84%E7%88%B1%E6%83%85"
	}
	
	,
	
    
	{
		"title" : "《谭艳   光明》　2014/08/14　其他",
		"url" : "/m/%E8%B0%AD%E8%89%B3-%E5%85%89%E6%98%8E"
	}
	
	,
	
    
	{
		"title" : "《谭咏麟   讲不出再见》　2014/08/14　其他",
		"url" : "/m/%E8%B0%AD%E5%92%8F%E9%BA%9F-%E8%AE%B2%E4%B8%8D%E5%87%BA%E5%86%8D%E8%A7%81"
	}
	
	,
	
    
	{
		"title" : "《谢霆锋   黄种人》　2014/08/14　其他",
		"url" : "/m/%E8%B0%A2%E9%9C%86%E9%94%8B-%E9%BB%84%E7%A7%8D%E4%BA%BA"
	}
	
	,
	
    
	{
		"title" : "《谢霆锋   谢谢你的爱1999》　2014/08/14　其他",
		"url" : "/m/%E8%B0%A2%E9%9C%86%E9%94%8B-%E8%B0%A2%E8%B0%A2%E4%BD%A0%E7%9A%84%E7%88%B11999"
	}
	
	,
	
    
	{
		"title" : "《谢霆锋   活着viva》　2014/08/14　其他",
		"url" : "/m/%E8%B0%A2%E9%9C%86%E9%94%8B-%E6%B4%BB%E7%9D%80Viva"
	}
	
	,
	
    
	{
		"title" : "《谢霆锋   因为爱所以爱》　2014/08/14　其他",
		"url" : "/m/%E8%B0%A2%E9%9C%86%E9%94%8B-%E5%9B%A0%E4%B8%BA%E7%88%B1%E6%89%80%E4%BB%A5%E7%88%B1"
	}
	
	,
	
    
	{
		"title" : "《谢安琪   钟无艳》　2014/08/14　其他",
		"url" : "/m/%E8%B0%A2%E5%AE%89%E7%90%AA-%E9%92%9F%E6%97%A0%E8%89%B3"
	}
	
	,
	
    
	{
		"title" : "《许巍   曾经的你》　2014/08/14　其他",
		"url" : "/m/%E8%AE%B8%E5%B7%8D-%E6%9B%BE%E7%BB%8F%E7%9A%84%E4%BD%A0"
	}
	
	,
	
    
	{
		"title" : "《许嵩 何曼婷   素颜》　2014/08/14　其他",
		"url" : "/m/%E8%AE%B8%E5%B5%A9-%E4%BD%95%E6%9B%BC%E5%A9%B7-%E7%B4%A0%E9%A2%9C"
	}
	
	,
	
    
	{
		"title" : "《许嵩   雅俗共赏》　2014/08/14　其他",
		"url" : "/m/%E8%AE%B8%E5%B5%A9-%E9%9B%85%E4%BF%97%E5%85%B1%E8%B5%8F"
	}
	
	,
	
    
	{
		"title" : "《誓言   求佛》　2014/08/14　其他",
		"url" : "/m/%E8%AA%93%E8%A8%80-%E6%B1%82%E4%BD%9B"
	}
	
	,
	
    
	{
		"title" : "《袁娅维   说散就散 (前任3)》　2014/08/14　其他",
		"url" : "/m/%E8%A2%81%E5%A8%85%E7%BB%B4-%E8%AF%B4%E6%95%A3%E5%B0%B1%E6%95%A3-(%E5%89%8D%E4%BB%BB3)"
	}
	
	,
	
    
	{
		"title" : "《街道办gdc _ 欧阳耀莹   春娇与志明》　2014/08/14　其他",
		"url" : "/m/%E8%A1%97%E9%81%93%E5%8A%9EGDC-_-%E6%AC%A7%E9%98%B3%E8%80%80%E8%8E%B9-%E6%98%A5%E5%A8%87%E4%B8%8E%E5%BF%97%E6%98%8E"
	}
	
	,
	
    
	{
		"title" : "《薛晓枫   最后一次》　2014/08/14　其他",
		"url" : "/m/%E8%96%9B%E6%99%93%E6%9E%AB-%E6%9C%80%E5%90%8E%E4%B8%80%E6%AC%A1"
	}
	
	,
	
    
	{
		"title" : "《薛之谦   认真的雪》　2014/08/14　其他",
		"url" : "/m/%E8%96%9B%E4%B9%8B%E8%B0%A6-%E8%AE%A4%E7%9C%9F%E7%9A%84%E9%9B%AA"
	}
	
	,
	
    
	{
		"title" : "《薛之谦   演员》　2014/08/14　其他",
		"url" : "/m/%E8%96%9B%E4%B9%8B%E8%B0%A6-%E6%BC%94%E5%91%98"
	}
	
	,
	
    
	{
		"title" : "《蔡卓妍   二缺一 (粤语)》　2014/08/14　其他",
		"url" : "/m/%E8%94%A1%E5%8D%93%E5%A6%8D-%E4%BA%8C%E7%BC%BA%E4%B8%80-(%E7%B2%A4%E8%AF%AD)"
	}
	
	,
	
    
	{
		"title" : "《蔡卓妍   二缺一 (国语)》　2014/08/14　其他",
		"url" : "/m/%E8%94%A1%E5%8D%93%E5%A6%8D-%E4%BA%8C%E7%BC%BA%E4%B8%80-(%E5%9B%BD%E8%AF%AD)"
	}
	
	,
	
    
	{
		"title" : "《蔡依林   说爱你》　2014/08/14　其他",
		"url" : "/m/%E8%94%A1%E4%BE%9D%E6%9E%97-%E8%AF%B4%E7%88%B1%E4%BD%A0"
	}
	
	,
	
    
	{
		"title" : "《蔡依林   特务j》　2014/08/14　其他",
		"url" : "/m/%E8%94%A1%E4%BE%9D%E6%9E%97-%E7%89%B9%E5%8A%A1J"
	}
	
	,
	
    
	{
		"title" : "《蔡依林   爱情三十六计》　2014/08/14　其他",
		"url" : "/m/%E8%94%A1%E4%BE%9D%E6%9E%97-%E7%88%B1%E6%83%85%E4%B8%89%E5%8D%81%E5%85%AD%E8%AE%A1"
	}
	
	,
	
    
	{
		"title" : "《蔡依林   倒带》　2014/08/14　其他",
		"url" : "/m/%E8%94%A1%E4%BE%9D%E6%9E%97-%E5%80%92%E5%B8%A6"
	}
	
	,
	
    
	{
		"title" : "《蔡依林   play我呸》　2014/08/14　其他",
		"url" : "/m/%E8%94%A1%E4%BE%9D%E6%9E%97-Play%E6%88%91%E5%91%B8"
	}
	
	,
	
    
	{
		"title" : "《蒋雪儿   莫问归期》　2014/08/14　其他",
		"url" : "/m/%E8%92%8B%E9%9B%AA%E5%84%BF-%E8%8E%AB%E9%97%AE%E5%BD%92%E6%9C%9F"
	}
	
	,
	
    
	{
		"title" : "《萧亚轩   类似爱情》　2014/08/14　其他",
		"url" : "/m/%E8%90%A7%E4%BA%9A%E8%BD%A9-%E7%B1%BB%E4%BC%BC%E7%88%B1%E6%83%85"
	}
	
	,
	
    
	{
		"title" : "《萧亚轩   爱的主打歌》　2014/08/14　其他",
		"url" : "/m/%E8%90%A7%E4%BA%9A%E8%BD%A9-%E7%88%B1%E7%9A%84%E4%B8%BB%E6%89%93%E6%AD%8C"
	}
	
	,
	
    
	{
		"title" : "《萧亚轩   最熟悉的陌生人》　2014/08/14　其他",
		"url" : "/m/%E8%90%A7%E4%BA%9A%E8%BD%A9-%E6%9C%80%E7%86%9F%E6%82%89%E7%9A%84%E9%99%8C%E7%94%9F%E4%BA%BA"
	}
	
	,
	
    
	{
		"title" : "《萌萌哒天团   帝都》　2014/08/14　其他",
		"url" : "/m/%E8%90%8C%E8%90%8C%E5%93%92%E5%A4%A9%E5%9B%A2-%E5%B8%9D%E9%83%BD"
	}
	
	,
	
    
	{
		"title" : "《莫文蔚   阴天》　2014/08/14　其他",
		"url" : "/m/%E8%8E%AB%E6%96%87%E8%94%9A-%E9%98%B4%E5%A4%A9"
	}
	
	,
	
    
	{
		"title" : "《莫文蔚   电台情歌》　2014/08/14　其他",
		"url" : "/m/%E8%8E%AB%E6%96%87%E8%94%9A-%E7%94%B5%E5%8F%B0%E6%83%85%E6%AD%8C"
	}
	
	,
	
    
	{
		"title" : "《莫文蔚   扶摇》　2014/08/14　其他",
		"url" : "/m/%E8%8E%AB%E6%96%87%E8%94%9A-%E6%89%B6%E6%91%87"
	}
	
	,
	
    
	{
		"title" : "《范逸臣   放生》　2014/08/14　其他",
		"url" : "/m/%E8%8C%83%E9%80%B8%E8%87%A3-%E6%94%BE%E7%94%9F"
	}
	
	,
	
    
	{
		"title" : "《范玮琪 _ 张韶涵   如果的事》　2014/08/14　其他",
		"url" : "/m/%E8%8C%83%E7%8E%AE%E7%90%AA-_-%E5%BC%A0%E9%9F%B6%E6%B6%B5-%E5%A6%82%E6%9E%9C%E7%9A%84%E4%BA%8B"
	}
	
	,
	
    
	{
		"title" : "《花粥,王胜娚   出山》　2014/08/14　其他",
		"url" : "/m/%E8%8A%B1%E7%B2%A5,%E7%8E%8B%E8%83%9C%E5%A8%9A-%E5%87%BA%E5%B1%B1"
	}
	
	,
	
    
	{
		"title" : "《花粥 马雨阳   盗将行》　2014/08/14　其他",
		"url" : "/m/%E8%8A%B1%E7%B2%A5-%E9%A9%AC%E9%9B%A8%E9%98%B3-%E7%9B%97%E5%B0%86%E8%A1%8C"
	}
	
	,
	
    
	{
		"title" : "《花僮   笑纳》　2014/08/14　其他",
		"url" : "/m/%E8%8A%B1%E5%83%AE-%E7%AC%91%E7%BA%B3"
	}
	
	,
	
    
	{
		"title" : "《花僮   浪子闲话》　2014/08/14　其他",
		"url" : "/m/%E8%8A%B1%E5%83%AE-%E6%B5%AA%E5%AD%90%E9%97%B2%E8%AF%9D"
	}
	
	,
	
    
	{
		"title" : "《胡歌   逍遥叹》　2014/08/14　其他",
		"url" : "/m/%E8%83%A1%E6%AD%8C-%E9%80%8D%E9%81%A5%E5%8F%B9"
	}
	
	,
	
    
	{
		"title" : "《胡歌   敢不敢爱 (《梦幻诛仙》网游主题曲)》　2014/08/14　其他",
		"url" : "/m/%E8%83%A1%E6%AD%8C-%E6%95%A2%E4%B8%8D%E6%95%A2%E7%88%B1-(-%E6%A2%A6%E5%B9%BB%E8%AF%9B%E4%BB%99-%E7%BD%91%E6%B8%B8%E4%B8%BB%E9%A2%98%E6%9B%B2)"
	}
	
	,
	
    
	{
		"title" : "《胡歌   忘记时间》　2014/08/14　其他",
		"url" : "/m/%E8%83%A1%E6%AD%8C-%E5%BF%98%E8%AE%B0%E6%97%B6%E9%97%B4"
	}
	
	,
	
    
	{
		"title" : "《胡歌   一吻天荒》　2014/08/14　其他",
		"url" : "/m/%E8%83%A1%E6%AD%8C-%E4%B8%80%E5%90%BB%E5%A4%A9%E8%8D%92"
	}
	
	,
	
    
	{
		"title" : "《胡彦斌 _ 白举纲   单恋一枝花 (live)》　2014/08/14　其他",
		"url" : "/m/%E8%83%A1%E5%BD%A6%E6%96%8C-_-%E7%99%BD%E4%B8%BE%E7%BA%B2-%E5%8D%95%E6%81%8B%E4%B8%80%E6%9E%9D%E8%8A%B1-(Live)"
	}
	
	,
	
    
	{
		"title" : "《胡彦斌   诀别诗》　2014/08/14　其他",
		"url" : "/m/%E8%83%A1%E5%BD%A6%E6%96%8C-%E8%AF%80%E5%88%AB%E8%AF%97"
	}
	
	,
	
    
	{
		"title" : "《胡彦斌   红颜》　2014/08/14　其他",
		"url" : "/m/%E8%83%A1%E5%BD%A6%E6%96%8C-%E7%BA%A2%E9%A2%9C"
	}
	
	,
	
    
	{
		"title" : "《胡彦斌   月光》　2014/08/14　其他",
		"url" : "/m/%E8%83%A1%E5%BD%A6%E6%96%8C-%E6%9C%88%E5%85%89"
	}
	
	,
	
    
	{
		"title" : "《胡彦斌   你要的全拿走》　2014/08/14　其他",
		"url" : "/m/%E8%83%A1%E5%BD%A6%E6%96%8C-%E4%BD%A0%E8%A6%81%E7%9A%84%E5%85%A8%E6%8B%BF%E8%B5%B0"
	}
	
	,
	
    
	{
		"title" : "《胡66   空空如也》　2014/08/14　其他",
		"url" : "/m/%E8%83%A166-%E7%A9%BA%E7%A9%BA%E5%A6%82%E4%B9%9F"
	}
	
	,
	
    
	{
		"title" : "《胡66   浪人琵琶》　2014/08/14　其他",
		"url" : "/m/%E8%83%A166-%E6%B5%AA%E4%BA%BA%E7%90%B5%E7%90%B6"
	}
	
	,
	
    
	{
		"title" : "《胡66   后来遇见他》　2014/08/14　其他",
		"url" : "/m/%E8%83%A166-%E5%90%8E%E6%9D%A5%E9%81%87%E8%A7%81%E4%BB%96"
	}
	
	,
	
    
	{
		"title" : "《等什么君   难渡》　2014/08/14　其他",
		"url" : "/m/%E7%AD%89%E4%BB%80%E4%B9%88%E5%90%9B-%E9%9A%BE%E6%B8%A1"
	}
	
	,
	
    
	{
		"title" : "《等什么君   辞九门回忆》　2014/08/14　其他",
		"url" : "/m/%E7%AD%89%E4%BB%80%E4%B9%88%E5%90%9B-%E8%BE%9E%E4%B9%9D%E9%97%A8%E5%9B%9E%E5%BF%86"
	}
	
	,
	
    
	{
		"title" : "《等什么君   春庭雪》　2014/08/14　其他",
		"url" : "/m/%E7%AD%89%E4%BB%80%E4%B9%88%E5%90%9B-%E6%98%A5%E5%BA%AD%E9%9B%AA"
	}
	
	,
	
    
	{
		"title" : "《等什么君   归寻》　2014/08/14　其他",
		"url" : "/m/%E7%AD%89%E4%BB%80%E4%B9%88%E5%90%9B-%E5%BD%92%E5%AF%BB"
	}
	
	,
	
    
	{
		"title" : "《等什么君   天下》　2014/08/14　其他",
		"url" : "/m/%E7%AD%89%E4%BB%80%E4%B9%88%E5%90%9B-%E5%A4%A9%E4%B8%8B"
	}
	
	,
	
    
	{
		"title" : "《等什么君   关山酒》　2014/08/14　其他",
		"url" : "/m/%E7%AD%89%E4%BB%80%E4%B9%88%E5%90%9B-%E5%85%B3%E5%B1%B1%E9%85%92"
	}
	
	,
	
    
	{
		"title" : "《穆哲熙   自愈》　2014/08/14　其他",
		"url" : "/m/%E7%A9%86%E5%93%B2%E7%86%99-%E8%87%AA%E6%84%88"
	}
	
	,
	
    
	{
		"title" : "《程响   等你归来》　2014/08/14　其他",
		"url" : "/m/%E7%A8%8B%E5%93%8D-%E7%AD%89%E4%BD%A0%E5%BD%92%E6%9D%A5"
	}
	
	,
	
    
	{
		"title" : "《程响   时光洪流》　2014/08/14　其他",
		"url" : "/m/%E7%A8%8B%E5%93%8D-%E6%97%B6%E5%85%89%E6%B4%AA%E6%B5%81"
	}
	
	,
	
    
	{
		"title" : "《程响   新娘不是我》　2014/08/14　其他",
		"url" : "/m/%E7%A8%8B%E5%93%8D-%E6%96%B0%E5%A8%98%E4%B8%8D%E6%98%AF%E6%88%91"
	}
	
	,
	
    
	{
		"title" : "《程响   彻悟》　2014/08/14　其他",
		"url" : "/m/%E7%A8%8B%E5%93%8D-%E5%BD%BB%E6%82%9F"
	}
	
	,
	
    
	{
		"title" : "《程响   四季予你》　2014/08/14　其他",
		"url" : "/m/%E7%A8%8B%E5%93%8D-%E5%9B%9B%E5%AD%A3%E4%BA%88%E4%BD%A0"
	}
	
	,
	
    
	{
		"title" : "《程响   世界这么大还是遇见你》　2014/08/14　其他",
		"url" : "/m/%E7%A8%8B%E5%93%8D-%E4%B8%96%E7%95%8C%E8%BF%99%E4%B9%88%E5%A4%A7%E8%BF%98%E6%98%AF%E9%81%87%E8%A7%81%E4%BD%A0"
	}
	
	,
	
    
	{
		"title" : "《程响   不再联系》　2014/08/14　其他",
		"url" : "/m/%E7%A8%8B%E5%93%8D-%E4%B8%8D%E5%86%8D%E8%81%94%E7%B3%BB"
	}
	
	,
	
    
	{
		"title" : "《程响   三生缘》　2014/08/14　其他",
		"url" : "/m/%E7%A8%8B%E5%93%8D-%E4%B8%89%E7%94%9F%E7%BC%98"
	}
	
	,
	
    
	{
		"title" : "《程jiajia   别错过》　2014/08/14　其他",
		"url" : "/m/%E7%A8%8Bjiajia-%E5%88%AB%E9%94%99%E8%BF%87"
	}
	
	,
	
    
	{
		"title" : "《秦海清   不如》　2014/08/14　其他",
		"url" : "/m/%E7%A7%A6%E6%B5%B7%E6%B8%85-%E4%B8%8D%E5%A6%82"
	}
	
	,
	
    
	{
		"title" : "《盖君炎   我想要》　2014/08/14　其他",
		"url" : "/m/%E7%9B%96%E5%90%9B%E7%82%8E-%E6%88%91%E6%83%B3%E8%A6%81"
	}
	
	,
	
    
	{
		"title" : "《白玛多吉   梦回云南》　2014/08/14　其他",
		"url" : "/m/%E7%99%BD%E7%8E%9B%E5%A4%9A%E5%90%89-%E6%A2%A6%E5%9B%9E%E4%BA%91%E5%8D%97"
	}
	
	,
	
    
	{
		"title" : "《白小白 _ 球球   宠爱吖》　2014/08/14　其他",
		"url" : "/m/%E7%99%BD%E5%B0%8F%E7%99%BD-_-%E7%90%83%E7%90%83-%E5%AE%A0%E7%88%B1%E5%90%96"
	}
	
	,
	
    
	{
		"title" : "《白小白   爱不得忘不舍》　2014/08/14　其他",
		"url" : "/m/%E7%99%BD%E5%B0%8F%E7%99%BD-%E7%88%B1%E4%B8%8D%E5%BE%97%E5%BF%98%E4%B8%8D%E8%88%8D"
	}
	
	,
	
    
	{
		"title" : "《白小白   最美情侣》　2014/08/14　其他",
		"url" : "/m/%E7%99%BD%E5%B0%8F%E7%99%BD-%E6%9C%80%E7%BE%8E%E6%83%85%E4%BE%A3"
	}
	
	,
	
    
	{
		"title" : "《白小白   最后我们没在一起》　2014/08/14　其他",
		"url" : "/m/%E7%99%BD%E5%B0%8F%E7%99%BD-%E6%9C%80%E5%90%8E%E6%88%91%E4%BB%AC%E6%B2%A1%E5%9C%A8%E4%B8%80%E8%B5%B7"
	}
	
	,
	
    
	{
		"title" : "《白小白   我爱你不问归期》　2014/08/14　其他",
		"url" : "/m/%E7%99%BD%E5%B0%8F%E7%99%BD-%E6%88%91%E7%88%B1%E4%BD%A0%E4%B8%8D%E9%97%AE%E5%BD%92%E6%9C%9F"
	}
	
	,
	
    
	{
		"title" : "《白小白   我们终究是错过》　2014/08/14　其他",
		"url" : "/m/%E7%99%BD%E5%B0%8F%E7%99%BD-%E6%88%91%E4%BB%AC%E7%BB%88%E7%A9%B6%E6%98%AF%E9%94%99%E8%BF%87"
	}
	
	,
	
    
	{
		"title" : "《白小白   会不会》　2014/08/14　其他",
		"url" : "/m/%E7%99%BD%E5%B0%8F%E7%99%BD-%E4%BC%9A%E4%B8%8D%E4%BC%9A"
	}
	
	,
	
    
	{
		"title" : "《田馥甄   爱了很久的朋友》　2014/08/14　其他",
		"url" : "/m/%E7%94%B0%E9%A6%A5%E7%94%84-%E7%88%B1%E4%BA%86%E5%BE%88%E4%B9%85%E7%9A%84%E6%9C%8B%E5%8F%8B"
	}
	
	,
	
    
	{
		"title" : "《田馥甄   小幸运》　2014/08/14　其他",
		"url" : "/m/%E7%94%B0%E9%A6%A5%E7%94%84-%E5%B0%8F%E5%B9%B8%E8%BF%90"
	}
	
	,
	
    
	{
		"title" : "《田馥甄   寂寞寂寞就好》　2014/08/14　其他",
		"url" : "/m/%E7%94%B0%E9%A6%A5%E7%94%84-%E5%AF%82%E5%AF%9E%E5%AF%82%E5%AF%9E%E5%B0%B1%E5%A5%BD"
	}
	
	,
	
    
	{
		"title" : "《田馥甄   你就不要想起我》　2014/08/14　其他",
		"url" : "/m/%E7%94%B0%E9%A6%A5%E7%94%84-%E4%BD%A0%E5%B0%B1%E4%B8%8D%E8%A6%81%E6%83%B3%E8%B5%B7%E6%88%91"
	}
	
	,
	
    
	{
		"title" : "《玖月奇迹   中国范儿》　2014/08/14　其他",
		"url" : "/m/%E7%8E%96%E6%9C%88%E5%A5%87%E8%BF%B9-%E4%B8%AD%E5%9B%BD%E8%8C%83%E5%84%BF"
	}
	
	,
	
    
	{
		"title" : "《王靖雯不胖   爱，存在》　2014/08/14　其他",
		"url" : "/m/%E7%8E%8B%E9%9D%96%E9%9B%AF%E4%B8%8D%E8%83%96-%E7%88%B1-%E5%AD%98%E5%9C%A8"
	}
	
	,
	
    
	{
		"title" : "《王靖雯不胖   沦陷》　2014/08/14　其他",
		"url" : "/m/%E7%8E%8B%E9%9D%96%E9%9B%AF%E4%B8%8D%E8%83%96-%E6%B2%A6%E9%99%B7"
	}
	
	,
	
    
	{
		"title" : "《王靖雯不胖   善变》　2014/08/14　其他",
		"url" : "/m/%E7%8E%8B%E9%9D%96%E9%9B%AF%E4%B8%8D%E8%83%96-%E5%96%84%E5%8F%98"
	}
	
	,
	
    
	{
		"title" : "《王靖雯不胖   不知所措》　2014/08/14　其他",
		"url" : "/m/%E7%8E%8B%E9%9D%96%E9%9B%AF%E4%B8%8D%E8%83%96-%E4%B8%8D%E7%9F%A5%E6%89%80%E6%8E%AA"
	}
	
	,
	
    
	{
		"title" : "《王贰浪   像鱼》　2014/08/14　其他",
		"url" : "/m/%E7%8E%8B%E8%B4%B0%E6%B5%AA-%E5%83%8F%E9%B1%BC"
	}
	
	,
	
    
	{
		"title" : "《王理文   庸人自扰》　2014/08/14　其他",
		"url" : "/m/%E7%8E%8B%E7%90%86%E6%96%87-%E5%BA%B8%E4%BA%BA%E8%87%AA%E6%89%B0"
	}
	
	,
	
    
	{
		"title" : "《王忻辰 _ 苏星婕   清空》　2014/08/14　其他",
		"url" : "/m/%E7%8E%8B%E5%BF%BB%E8%BE%B0-_-%E8%8B%8F%E6%98%9F%E5%A9%95-%E6%B8%85%E7%A9%BA"
	}
	
	,
	
    
	{
		"title" : "《王心凌   第一次爱的人》　2014/08/14　其他",
		"url" : "/m/%E7%8E%8B%E5%BF%83%E5%87%8C-%E7%AC%AC%E4%B8%80%E6%AC%A1%E7%88%B1%E7%9A%84%E4%BA%BA"
	}
	
	,
	
    
	{
		"title" : "《王强   秋天不回来》　2014/08/14　其他",
		"url" : "/m/%E7%8E%8B%E5%BC%BA-%E7%A7%8B%E5%A4%A9%E4%B8%8D%E5%9B%9E%E6%9D%A5"
	}
	
	,
	
    
	{
		"title" : "《王小帅   最近》　2014/08/14　其他",
		"url" : "/m/%E7%8E%8B%E5%B0%8F%E5%B8%85-%E6%9C%80%E8%BF%91"
	}
	
	,
	
    
	{
		"title" : "《王娅   爱情错觉》　2014/08/14　其他",
		"url" : "/m/%E7%8E%8B%E5%A8%85-%E7%88%B1%E6%83%85%E9%94%99%E8%A7%89"
	}
	
	,
	
    
	{
		"title" : "《王大毛   去年夏天》　2014/08/14　其他",
		"url" : "/m/%E7%8E%8B%E5%A4%A7%E6%AF%9B-%E5%8E%BB%E5%B9%B4%E5%A4%8F%E5%A4%A9"
	}
	
	,
	
    
	{
		"title" : "《王力宏 谭维维   bridge of faith》　2014/08/14　其他",
		"url" : "/m/%E7%8E%8B%E5%8A%9B%E5%AE%8F-%E8%B0%AD%E7%BB%B4%E7%BB%B4-Bridge-of-Faith"
	}
	
	,
	
    
	{
		"title" : "《王力宏 _ 谭维维   缘分一道桥》　2014/08/14　其他",
		"url" : "/m/%E7%8E%8B%E5%8A%9B%E5%AE%8F-_-%E8%B0%AD%E7%BB%B4%E7%BB%B4-%E7%BC%98%E5%88%86%E4%B8%80%E9%81%93%E6%A1%A5"
	}
	
	,
	
    
	{
		"title" : "《王冰洋   飞舞》　2014/08/14　其他",
		"url" : "/m/%E7%8E%8B%E5%86%B0%E6%B4%8B-%E9%A3%9E%E8%88%9E"
	}
	
	,
	
    
	{
		"title" : "《王冕   勉为其难》　2014/08/14　其他",
		"url" : "/m/%E7%8E%8B%E5%86%95-%E5%8B%89%E4%B8%BA%E5%85%B6%E9%9A%BE"
	}
	
	,
	
    
	{
		"title" : "《王冕   三十岁的男人》　2014/08/14　其他",
		"url" : "/m/%E7%8E%8B%E5%86%95-%E4%B8%89%E5%8D%81%E5%B2%81%E7%9A%84%E7%94%B7%E4%BA%BA"
	}
	
	,
	
    
	{
		"title" : "《玄觞   大浪淘沙》　2014/08/14　其他",
		"url" : "/m/%E7%8E%84%E8%A7%9E-%E5%A4%A7%E6%B5%AA%E6%B7%98%E6%B2%99"
	}
	
	,
	
    
	{
		"title" : "《牧马城市   毛不易》　2014/08/14　其他",
		"url" : "/m/%E7%89%A7%E9%A9%AC%E5%9F%8E%E5%B8%82-%E6%AF%9B%E4%B8%8D%E6%98%93"
	}
	
	,
	
    
	{
		"title" : "《火箭少女101   卡路里》　2014/08/14　其他",
		"url" : "/m/%E7%81%AB%E7%AE%AD%E5%B0%91%E5%A5%B3101-%E5%8D%A1%E8%B7%AF%E9%87%8C"
	}
	
	,
	
    
	{
		"title" : "《滨崎步 (浜崎あゆみ)   my all》　2014/08/14　其他",
		"url" : "/m/%E6%BB%A8%E5%B4%8E%E6%AD%A5-(%E6%B5%9C%E5%B4%8E%E3%81%82%E3%82%86%E3%81%BF)-MY-ALL"
	}
	
	,
	
    
	{
		"title" : "《温奕心   一路生花》　2014/08/14　其他",
		"url" : "/m/%E6%B8%A9%E5%A5%95%E5%BF%83-%E4%B8%80%E8%B7%AF%E7%94%9F%E8%8A%B1"
	}
	
	,
	
    
	{
		"title" : "《海来阿木   点歌的人》　2014/08/14　其他",
		"url" : "/m/%E6%B5%B7%E6%9D%A5%E9%98%BF%E6%9C%A8-%E7%82%B9%E6%AD%8C%E7%9A%84%E4%BA%BA"
	}
	
	,
	
    
	{
		"title" : "《海伦   桥边姑娘》　2014/08/14　其他",
		"url" : "/m/%E6%B5%B7%E4%BC%A6-%E6%A1%A5%E8%BE%B9%E5%A7%91%E5%A8%98"
	}
	
	,
	
    
	{
		"title" : "《汪苏泷 _ by2   有点甜》　2014/08/14　其他",
		"url" : "/m/%E6%B1%AA%E8%8B%8F%E6%B3%B7-_-BY2-%E6%9C%89%E7%82%B9%E7%94%9C"
	}
	
	,
	
    
	{
		"title" : "《汤晶锦   天亮了》　2014/08/14　其他",
		"url" : "/m/%E6%B1%A4%E6%99%B6%E9%94%A6-%E5%A4%A9%E4%BA%AE%E4%BA%86"
	}
	
	,
	
    
	{
		"title" : "《毛阿敏   相思》　2014/08/14　其他",
		"url" : "/m/%E6%AF%9B%E9%98%BF%E6%95%8F-%E7%9B%B8%E6%80%9D"
	}
	
	,
	
    
	{
		"title" : "《毛不易   消愁》　2014/08/14　其他",
		"url" : "/m/%E6%AF%9B%E4%B8%8D%E6%98%93-%E6%B6%88%E6%84%81"
	}
	
	,
	
    
	{
		"title" : "《毛不易   像我这样的人》　2014/08/14　其他",
		"url" : "/m/%E6%AF%9B%E4%B8%8D%E6%98%93-%E5%83%8F%E6%88%91%E8%BF%99%E6%A0%B7%E7%9A%84%E4%BA%BA"
	}
	
	,
	
    
	{
		"title" : "《毛不易   不染》　2014/08/14　其他",
		"url" : "/m/%E6%AF%9B%E4%B8%8D%E6%98%93-%E4%B8%8D%E6%9F%93"
	}
	
	,
	
    
	{
		"title" : "《棉子   勇气》　2014/08/14　其他",
		"url" : "/m/%E6%A3%89%E5%AD%90-%E5%8B%87%E6%B0%94"
	}
	
	,
	
    
	{
		"title" : "《梦然   没有你陪伴真的好孤单》　2014/08/14　其他",
		"url" : "/m/%E6%A2%A6%E7%84%B6-%E6%B2%A1%E6%9C%89%E4%BD%A0%E9%99%AA%E4%BC%B4%E7%9C%9F%E7%9A%84%E5%A5%BD%E5%AD%A4%E5%8D%95"
	}
	
	,
	
    
	{
		"title" : "《梦然   少年》　2014/08/14　其他",
		"url" : "/m/%E6%A2%A6%E7%84%B6-%E5%B0%91%E5%B9%B4"
	}
	
	,
	
    
	{
		"title" : "《梦然   北京烟火》　2014/08/14　其他",
		"url" : "/m/%E6%A2%A6%E7%84%B6-%E5%8C%97%E4%BA%AC%E7%83%9F%E7%81%AB"
	}
	
	,
	
    
	{
		"title" : "《梦涵   爱的故事上集》　2014/08/14　其他",
		"url" : "/m/%E6%A2%A6%E6%B6%B5-%E7%88%B1%E7%9A%84%E6%95%85%E4%BA%8B%E4%B8%8A%E9%9B%86"
	}
	
	,
	
    
	{
		"title" : "《梁静茹   情歌》　2014/08/14　其他",
		"url" : "/m/%E6%A2%81%E9%9D%99%E8%8C%B9-%E6%83%85%E6%AD%8C"
	}
	
	,
	
    
	{
		"title" : "《梁汉文   七友》　2014/08/14　其他",
		"url" : "/m/%E6%A2%81%E6%B1%89%E6%96%87-%E4%B8%83%E5%8F%8B"
	}
	
	,
	
    
	{
		"title" : "《柳岩   孙尚香》　2014/08/14　其他",
		"url" : "/m/%E6%9F%B3%E5%B2%A9-%E5%AD%99%E5%B0%9A%E9%A6%99"
	}
	
	,
	
    
	{
		"title" : "《林志炫   单身情歌》　2014/08/14　其他",
		"url" : "/m/%E6%9E%97%E5%BF%97%E7%82%AB-%E5%8D%95%E8%BA%AB%E6%83%85%E6%AD%8C"
	}
	
	,
	
    
	{
		"title" : "《林忆莲   至少还有你》　2014/08/14　其他",
		"url" : "/m/%E6%9E%97%E5%BF%86%E8%8E%B2-%E8%87%B3%E5%B0%91%E8%BF%98%E6%9C%89%E4%BD%A0"
	}
	
	,
	
    
	{
		"title" : "《林俊杰、蔡卓妍   小酒窝》　2014/08/14　其他",
		"url" : "/m/%E6%9E%97%E4%BF%8A%E6%9D%B0-%E8%94%A1%E5%8D%93%E5%A6%8D-%E5%B0%8F%E9%85%92%E7%AA%9D"
	}
	
	,
	
    
	{
		"title" : "《林俊杰   关键词》　2014/08/14　其他",
		"url" : "/m/%E6%9E%97%E4%BF%8A%E6%9D%B0-%E5%85%B3%E9%94%AE%E8%AF%8D"
	}
	
	,
	
    
	{
		"title" : "《杨蔓 _ 雨宗林   你的样子》　2014/08/14　其他",
		"url" : "/m/%E6%9D%A8%E8%94%93-_-%E9%9B%A8%E5%AE%97%E6%9E%97-%E4%BD%A0%E7%9A%84%E6%A0%B7%E5%AD%90"
	}
	
	,
	
    
	{
		"title" : "《杨胖雨   情深深雨濛濛》　2014/08/14　其他",
		"url" : "/m/%E6%9D%A8%E8%83%96%E9%9B%A8-%E6%83%85%E6%B7%B1%E6%B7%B1%E9%9B%A8%E6%BF%9B%E6%BF%9B"
	}
	
	,
	
    
	{
		"title" : "《杨小壮 _ 鹏鹏音乐   口是心非》　2014/08/14　其他",
		"url" : "/m/%E6%9D%A8%E5%B0%8F%E5%A3%AE-_-%E9%B9%8F%E9%B9%8F%E9%9F%B3%E4%B9%90-%E5%8F%A3%E6%98%AF%E5%BF%83%E9%9D%9E"
	}
	
	,
	
    
	{
		"title" : "《杨小壮 _ 鹏鹏   让我欢喜让我忧》　2014/08/14　其他",
		"url" : "/m/%E6%9D%A8%E5%B0%8F%E5%A3%AE-_-%E9%B9%8F%E9%B9%8F-%E8%AE%A9%E6%88%91%E6%AC%A2%E5%96%9C%E8%AE%A9%E6%88%91%E5%BF%A7"
	}
	
	,
	
    
	{
		"title" : "《杨宗纬 _ 张碧晨   凉凉》　2014/08/14　其他",
		"url" : "/m/%E6%9D%A8%E5%AE%97%E7%BA%AC-_-%E5%BC%A0%E7%A2%A7%E6%99%A8-%E5%87%89%E5%87%89"
	}
	
	,
	
    
	{
		"title" : "《杨宗纬   一次就好》　2014/08/14　其他",
		"url" : "/m/%E6%9D%A8%E5%AE%97%E7%BA%AC-%E4%B8%80%E6%AC%A1%E5%B0%B1%E5%A5%BD"
	}
	
	,
	
    
	{
		"title" : "《杨千嬅   处处吻》　2014/08/14　其他",
		"url" : "/m/%E6%9D%A8%E5%8D%83%E5%AC%85-%E5%A4%84%E5%A4%84%E5%90%BB"
	}
	
	,
	
    
	{
		"title" : "《杨丞琳   雨爱》　2014/08/14　其他",
		"url" : "/m/%E6%9D%A8%E4%B8%9E%E7%90%B3-%E9%9B%A8%E7%88%B1"
	}
	
	,
	
    
	{
		"title" : "《杨丞琳   仰望》　2014/08/14　其他",
		"url" : "/m/%E6%9D%A8%E4%B8%9E%E7%90%B3-%E4%BB%B0%E6%9C%9B"
	}
	
	,
	
    
	{
		"title" : "《李袁杰   离人愁》　2014/08/14　其他",
		"url" : "/m/%E6%9D%8E%E8%A2%81%E6%9D%B0-%E7%A6%BB%E4%BA%BA%E6%84%81"
	}
	
	,
	
    
	{
		"title" : "《李荣浩   麻雀》　2014/08/14　其他",
		"url" : "/m/%E6%9D%8E%E8%8D%A3%E6%B5%A9-%E9%BA%BB%E9%9B%80"
	}
	
	,
	
    
	{
		"title" : "《李翊君   雨蝶》　2014/08/14　其他",
		"url" : "/m/%E6%9D%8E%E7%BF%8A%E5%90%9B-%E9%9B%A8%E8%9D%B6"
	}
	
	,
	
    
	{
		"title" : "《李翊君   诺言》　2014/08/14　其他",
		"url" : "/m/%E6%9D%8E%E7%BF%8A%E5%90%9B-%E8%AF%BA%E8%A8%80"
	}
	
	,
	
    
	{
		"title" : "《李玟 _ 周杰伦   刀马旦》　2014/08/14　其他",
		"url" : "/m/%E6%9D%8E%E7%8E%9F-_-%E5%91%A8%E6%9D%B0%E4%BC%A6-%E5%88%80%E9%A9%AC%E6%97%A6"
	}
	
	,
	
    
	{
		"title" : "《李玟   叩叩》　2014/08/14　其他",
		"url" : "/m/%E6%9D%8E%E7%8E%9F-%E5%8F%A9%E5%8F%A9"
	}
	
	,
	
    
	{
		"title" : "《李玉刚   雨花石》　2014/08/14　其他",
		"url" : "/m/%E6%9D%8E%E7%8E%89%E5%88%9A-%E9%9B%A8%E8%8A%B1%E7%9F%B3"
	}
	
	,
	
    
	{
		"title" : "《李玉刚   清明上河图》　2014/08/14　其他",
		"url" : "/m/%E6%9D%8E%E7%8E%89%E5%88%9A-%E6%B8%85%E6%98%8E%E4%B8%8A%E6%B2%B3%E5%9B%BE"
	}
	
	,
	
    
	{
		"title" : "《李玉刚   新贵妃醉酒》　2014/08/14　其他",
		"url" : "/m/%E6%9D%8E%E7%8E%89%E5%88%9A-%E6%96%B0%E8%B4%B5%E5%A6%83%E9%86%89%E9%85%92"
	}
	
	,
	
    
	{
		"title" : "《李玉刚   刚好遇见你》　2014/08/14　其他",
		"url" : "/m/%E6%9D%8E%E7%8E%89%E5%88%9A-%E5%88%9A%E5%A5%BD%E9%81%87%E8%A7%81%E4%BD%A0"
	}
	
	,
	
    
	{
		"title" : "《李晓杰   朋友的酒》　2014/08/14　其他",
		"url" : "/m/%E6%9D%8E%E6%99%93%E6%9D%B0-%E6%9C%8B%E5%8F%8B%E7%9A%84%E9%85%92"
	}
	
	,
	
    
	{
		"title" : "《李晓杰   把酒倒满》　2014/08/14　其他",
		"url" : "/m/%E6%9D%8E%E6%99%93%E6%9D%B0-%E6%8A%8A%E9%85%92%E5%80%92%E6%BB%A1"
	}
	
	,
	
    
	{
		"title" : "《李宇春   蜀绣》　2014/08/14　其他",
		"url" : "/m/%E6%9D%8E%E5%AE%87%E6%98%A5-%E8%9C%80%E7%BB%A3"
	}
	
	,
	
    
	{
		"title" : "《李宇春   无价之姐》　2014/08/14　其他",
		"url" : "/m/%E6%9D%8E%E5%AE%87%E6%98%A5-%E6%97%A0%E4%BB%B7%E4%B9%8B%E5%A7%90"
	}
	
	,
	
    
	{
		"title" : "《李宇春   少年中国》　2014/08/14　其他",
		"url" : "/m/%E6%9D%8E%E5%AE%87%E6%98%A5-%E5%B0%91%E5%B9%B4%E4%B8%AD%E5%9B%BD"
	}
	
	,
	
    
	{
		"title" : "《李孝利   10 minutes (十分钟)》　2014/08/14　其他",
		"url" : "/m/%E6%9D%8E%E5%AD%9D%E5%88%A9-10-Minutes-(%E5%8D%81%E5%88%86%E9%92%9F)"
	}
	
	,
	
    
	{
		"title" : "《李克勤 _ 周深   天下有情人 (live)》　2014/08/14　其他",
		"url" : "/m/%E6%9D%8E%E5%85%8B%E5%8B%A4-_-%E5%91%A8%E6%B7%B1-%E5%A4%A9%E4%B8%8B%E6%9C%89%E6%83%85%E4%BA%BA-(Live)"
	}
	
	,
	
    
	{
		"title" : "《朴树   平凡之路》　2014/08/14　其他",
		"url" : "/m/%E6%9C%B4%E6%A0%91-%E5%B9%B3%E5%87%A1%E4%B9%8B%E8%B7%AF"
	}
	
	,
	
    
	{
		"title" : "《木小雅   可能否》　2014/08/14　其他",
		"url" : "/m/%E6%9C%A8%E5%B0%8F%E9%9B%85-%E5%8F%AF%E8%83%BD%E5%90%A6"
	}
	
	,
	
    
	{
		"title" : "《曾惜   讲真的》　2014/08/14　其他",
		"url" : "/m/%E6%9B%BE%E6%83%9C-%E8%AE%B2%E7%9C%9F%E7%9A%84"
	}
	
	,
	
    
	{
		"title" : "《曲肖冰   太阳 (正式版)》　2014/08/14　其他",
		"url" : "/m/%E6%9B%B2%E8%82%96%E5%86%B0-%E5%A4%AA%E9%98%B3-(%E6%AD%A3%E5%BC%8F%E7%89%88)"
	}
	
	,
	
    
	{
		"title" : "《曲肖冰   厚颜无耻》　2014/08/14　其他",
		"url" : "/m/%E6%9B%B2%E8%82%96%E5%86%B0-%E5%8E%9A%E9%A2%9C%E6%97%A0%E8%80%BB"
	}
	
	,
	
    
	{
		"title" : "《是七叔呢   半生雪》　2014/08/14　其他",
		"url" : "/m/%E6%98%AF%E4%B8%83%E5%8F%94%E5%91%A2-%E5%8D%8A%E7%94%9F%E9%9B%AA"
	}
	
	,
	
    
	{
		"title" : "《戴羽彤   来迟》　2014/08/14　其他",
		"url" : "/m/%E6%88%B4%E7%BE%BD%E5%BD%A4-%E6%9D%A5%E8%BF%9F"
	}
	
	,
	
    
	{
		"title" : "《慕容晓晓   黄梅戏》　2014/08/14　其他",
		"url" : "/m/%E6%85%95%E5%AE%B9%E6%99%93%E6%99%93-%E9%BB%84%E6%A2%85%E6%88%8F"
	}
	
	,
	
    
	{
		"title" : "《徐誉滕   等一分钟》　2014/08/14　其他",
		"url" : "/m/%E5%BE%90%E8%AA%89%E6%BB%95-%E7%AD%89%E4%B8%80%E5%88%86%E9%92%9F"
	}
	
	,
	
    
	{
		"title" : "《徐怀钰   踏浪》　2014/08/14　其他",
		"url" : "/m/%E5%BE%90%E6%80%80%E9%92%B0-%E8%B8%8F%E6%B5%AA"
	}
	
	,
	
    
	{
		"title" : "《徐怀钰   分飞》　2014/08/14　其他",
		"url" : "/m/%E5%BE%90%E6%80%80%E9%92%B0-%E5%88%86%E9%A3%9E"
	}
	
	,
	
    
	{
		"title" : "《徐心愉   自愈 (完整女声版_原唱_穆哲熙)》　2014/08/14　其他",
		"url" : "/m/%E5%BE%90%E5%BF%83%E6%84%89-%E8%87%AA%E6%84%88-(%E5%AE%8C%E6%95%B4%E5%A5%B3%E5%A3%B0%E7%89%88_%E5%8E%9F%E5%94%B1_%E7%A9%86%E5%93%B2%E7%86%99)"
	}
	
	,
	
    
	{
		"title" : "《张韶涵 _ 潘玮柏   快乐崇拜》　2014/08/14　其他",
		"url" : "/m/%E5%BC%A0%E9%9F%B6%E6%B6%B5-_-%E6%BD%98%E7%8E%AE%E6%9F%8F-%E5%BF%AB%E4%B9%90%E5%B4%87%E6%8B%9C"
	}
	
	,
	
    
	{
		"title" : "《张韶涵   香水百合》　2014/08/14　其他",
		"url" : "/m/%E5%BC%A0%E9%9F%B6%E6%B6%B5-%E9%A6%99%E6%B0%B4%E7%99%BE%E5%90%88"
	}
	
	,
	
    
	{
		"title" : "《张韶涵   隐形的翅膀》　2014/08/14　其他",
		"url" : "/m/%E5%BC%A0%E9%9F%B6%E6%B6%B5-%E9%9A%90%E5%BD%A2%E7%9A%84%E7%BF%85%E8%86%80"
	}
	
	,
	
    
	{
		"title" : "《张韶涵   破茧》　2014/08/14　其他",
		"url" : "/m/%E5%BC%A0%E9%9F%B6%E6%B6%B5-%E7%A0%B4%E8%8C%A7"
	}
	
	,
	
    
	{
		"title" : "《张韶涵   淋雨一直走》　2014/08/14　其他",
		"url" : "/m/%E5%BC%A0%E9%9F%B6%E6%B6%B5-%E6%B7%8B%E9%9B%A8%E4%B8%80%E7%9B%B4%E8%B5%B0"
	}
	
	,
	
    
	{
		"title" : "《张韶涵   欧若拉》　2014/08/14　其他",
		"url" : "/m/%E5%BC%A0%E9%9F%B6%E6%B6%B5-%E6%AC%A7%E8%8B%A5%E6%8B%89"
	}
	
	,
	
    
	{
		"title" : "《张韶涵   寓言》　2014/08/14　其他",
		"url" : "/m/%E5%BC%A0%E9%9F%B6%E6%B6%B5-%E5%AF%93%E8%A8%80"
	}
	
	,
	
    
	{
		"title" : "《张靓颖   饿狼传说 (live)》　2014/08/14　其他",
		"url" : "/m/%E5%BC%A0%E9%9D%93%E9%A2%96-%E9%A5%BF%E7%8B%BC%E4%BC%A0%E8%AF%B4-(Live)"
	}
	
	,
	
    
	{
		"title" : "《张靓颖   终于等到你》　2014/08/14　其他",
		"url" : "/m/%E5%BC%A0%E9%9D%93%E9%A2%96-%E7%BB%88%E4%BA%8E%E7%AD%89%E5%88%B0%E4%BD%A0"
	}
	
	,
	
    
	{
		"title" : "《张靓颖   画心》　2014/08/14　其他",
		"url" : "/m/%E5%BC%A0%E9%9D%93%E9%A2%96-%E7%94%BB%E5%BF%83"
	}
	
	,
	
    
	{
		"title" : "《张靓颖   燕归巢》　2014/08/14　其他",
		"url" : "/m/%E5%BC%A0%E9%9D%93%E9%A2%96-%E7%87%95%E5%BD%92%E5%B7%A2"
	}
	
	,
	
    
	{
		"title" : "《张靓颖   无字碑》　2014/08/14　其他",
		"url" : "/m/%E5%BC%A0%E9%9D%93%E9%A2%96-%E6%97%A0%E5%AD%97%E7%A2%91"
	}
	
	,
	
    
	{
		"title" : "《张靓颖   我的梦》　2014/08/14　其他",
		"url" : "/m/%E5%BC%A0%E9%9D%93%E9%A2%96-%E6%88%91%E7%9A%84%E6%A2%A6"
	}
	
	,
	
    
	{
		"title" : "《张靓颖   如果这就是爱情》　2014/08/14　其他",
		"url" : "/m/%E5%BC%A0%E9%9D%93%E9%A2%96-%E5%A6%82%E6%9E%9C%E8%BF%99%E5%B0%B1%E6%98%AF%E7%88%B1%E6%83%85"
	}
	
	,
	
    
	{
		"title" : "《张靓颖   一生一次心一动》　2014/08/14　其他",
		"url" : "/m/%E5%BC%A0%E9%9D%93%E9%A2%96-%E4%B8%80%E7%94%9F%E4%B8%80%E6%AC%A1%E5%BF%83%E4%B8%80%E5%8A%A8"
	}
	
	,
	
    
	{
		"title" : "《张靓颖   dream it possible》　2014/08/14　其他",
		"url" : "/m/%E5%BC%A0%E9%9D%93%E9%A2%96-Dream-It-Possible"
	}
	
	,
	
    
	{
		"title" : "《张芸京   偏爱》　2014/08/14　其他",
		"url" : "/m/%E5%BC%A0%E8%8A%B8%E4%BA%AC-%E5%81%8F%E7%88%B1"
	}
	
	,
	
    
	{
		"title" : "《张紫豪   可不可以》　2014/08/14　其他",
		"url" : "/m/%E5%BC%A0%E7%B4%AB%E8%B1%AA-%E5%8F%AF%E4%B8%8D%E5%8F%AF%E4%BB%A5"
	}
	
	,
	
    
	{
		"title" : "《张碧晨、杨宗纬   凉凉 (live)》　2014/08/14　其他",
		"url" : "/m/%E5%BC%A0%E7%A2%A7%E6%99%A8-%E6%9D%A8%E5%AE%97%E7%BA%AC-%E5%87%89%E5%87%89-(Live)"
	}
	
	,
	
    
	{
		"title" : "《张碧晨   如故》　2014/08/14　其他",
		"url" : "/m/%E5%BC%A0%E7%A2%A7%E6%99%A8-%E5%A6%82%E6%95%85"
	}
	
	,
	
    
	{
		"title" : "《张杰   逆战》　2014/08/14　其他",
		"url" : "/m/%E5%BC%A0%E6%9D%B0-%E9%80%86%E6%88%98"
	}
	
	,
	
    
	{
		"title" : "《张杰   少年中国说》　2014/08/14　其他",
		"url" : "/m/%E5%BC%A0%E6%9D%B0-%E5%B0%91%E5%B9%B4%E4%B8%AD%E5%9B%BD%E8%AF%B4"
	}
	
	,
	
    
	{
		"title" : "《张杰   天下》　2014/08/14　其他",
		"url" : "/m/%E5%BC%A0%E6%9D%B0-%E5%A4%A9%E4%B8%8B"
	}
	
	,
	
    
	{
		"title" : "《张杰   剑心》　2014/08/14　其他",
		"url" : "/m/%E5%BC%A0%E6%9D%B0-%E5%89%91%E5%BF%83"
	}
	
	,
	
    
	{
		"title" : "《张晓棠   苏幕遮》　2014/08/14　其他",
		"url" : "/m/%E5%BC%A0%E6%99%93%E6%A3%A0-%E8%8B%8F%E5%B9%95%E9%81%AE"
	}
	
	,
	
    
	{
		"title" : "《张宇   雨一直下》　2014/08/14　其他",
		"url" : "/m/%E5%BC%A0%E5%AE%87-%E9%9B%A8%E4%B8%80%E7%9B%B4%E4%B8%8B"
	}
	
	,
	
    
	{
		"title" : "《张宇   男人的好》　2014/08/14　其他",
		"url" : "/m/%E5%BC%A0%E5%AE%87-%E7%94%B7%E4%BA%BA%E7%9A%84%E5%A5%BD"
	}
	
	,
	
    
	{
		"title" : "《张宇   用心良苦》　2014/08/14　其他",
		"url" : "/m/%E5%BC%A0%E5%AE%87-%E7%94%A8%E5%BF%83%E8%89%AF%E8%8B%A6"
	}
	
	,
	
    
	{
		"title" : "《张宇   月亮惹的祸》　2014/08/14　其他",
		"url" : "/m/%E5%BC%A0%E5%AE%87-%E6%9C%88%E4%BA%AE%E6%83%B9%E7%9A%84%E7%A5%B8"
	}
	
	,
	
    
	{
		"title" : "《张宇   曲终人散》　2014/08/14　其他",
		"url" : "/m/%E5%BC%A0%E5%AE%87-%E6%9B%B2%E7%BB%88%E4%BA%BA%E6%95%A3"
	}
	
	,
	
    
	{
		"title" : "《张宇   大女人》　2014/08/14　其他",
		"url" : "/m/%E5%BC%A0%E5%AE%87-%E5%A4%A7%E5%A5%B3%E4%BA%BA"
	}
	
	,
	
    
	{
		"title" : "《张宇   囚鸟》　2014/08/14　其他",
		"url" : "/m/%E5%BC%A0%E5%AE%87-%E5%9B%9A%E9%B8%9F"
	}
	
	,
	
    
	{
		"title" : "《张宇   单恋一枝花》　2014/08/14　其他",
		"url" : "/m/%E5%BC%A0%E5%AE%87-%E5%8D%95%E6%81%8B%E4%B8%80%E6%9E%9D%E8%8A%B1"
	}
	
	,
	
    
	{
		"title" : "《张宇   一言难尽》　2014/08/14　其他",
		"url" : "/m/%E5%BC%A0%E5%AE%87-%E4%B8%80%E8%A8%80%E9%9A%BE%E5%B0%BD"
	}
	
	,
	
    
	{
		"title" : "《张含韵   酸酸甜甜就是我》　2014/08/14　其他",
		"url" : "/m/%E5%BC%A0%E5%90%AB%E9%9F%B5-%E9%85%B8%E9%85%B8%E7%94%9C%E7%94%9C%E5%B0%B1%E6%98%AF%E6%88%91"
	}
	
	,
	
    
	{
		"title" : "《张叶蕾   还是分开》　2014/08/14　其他",
		"url" : "/m/%E5%BC%A0%E5%8F%B6%E8%95%BE-%E8%BF%98%E6%98%AF%E5%88%86%E5%BC%80"
	}
	
	,
	
    
	{
		"title" : "《张卫健   虚虚实实》　2014/08/14　其他",
		"url" : "/m/%E5%BC%A0%E5%8D%AB%E5%81%A5-%E8%99%9A%E8%99%9A%E5%AE%9E%E5%AE%9E"
	}
	
	,
	
    
	{
		"title" : "《张卫健   真真假假》　2014/08/14　其他",
		"url" : "/m/%E5%BC%A0%E5%8D%AB%E5%81%A5-%E7%9C%9F%E7%9C%9F%E5%81%87%E5%81%87"
	}
	
	,
	
    
	{
		"title" : "《张卫健   孤独不苦》　2014/08/14　其他",
		"url" : "/m/%E5%BC%A0%E5%8D%AB%E5%81%A5-%E5%AD%A4%E7%8B%AC%E4%B8%8D%E8%8B%A6"
	}
	
	,
	
    
	{
		"title" : "《张卫健   信徒》　2014/08/14　其他",
		"url" : "/m/%E5%BC%A0%E5%8D%AB%E5%81%A5-%E4%BF%A1%E5%BE%92"
	}
	
	,
	
    
	{
		"title" : "《张卫健   你爱我像谁》　2014/08/14　其他",
		"url" : "/m/%E5%BC%A0%E5%8D%AB%E5%81%A5-%E4%BD%A0%E7%88%B1%E6%88%91%E5%83%8F%E8%B0%81"
	}
	
	,
	
    
	{
		"title" : "《张卫健   一辈子一场梦》　2014/08/14　其他",
		"url" : "/m/%E5%BC%A0%E5%8D%AB%E5%81%A5-%E4%B8%80%E8%BE%88%E5%AD%90%E4%B8%80%E5%9C%BA%E6%A2%A6"
	}
	
	,
	
    
	{
		"title" : "《张北北   拥抱你离去》　2014/08/14　其他",
		"url" : "/m/%E5%BC%A0%E5%8C%97%E5%8C%97-%E6%8B%A5%E6%8A%B1%E4%BD%A0%E7%A6%BB%E5%8E%BB"
	}
	
	,
	
    
	{
		"title" : "《廖晶   爱情小丑》　2014/08/14　其他",
		"url" : "/m/%E5%BB%96%E6%99%B6-%E7%88%B1%E6%83%85%E5%B0%8F%E4%B8%91"
	}
	
	,
	
    
	{
		"title" : "《庄心妍 _ 祁隆   一万个舍不得》　2014/08/14　其他",
		"url" : "/m/%E5%BA%84%E5%BF%83%E5%A6%8D-_-%E7%A5%81%E9%9A%86-%E4%B8%80%E4%B8%87%E4%B8%AA%E8%88%8D%E4%B8%8D%E5%BE%97"
	}
	
	,
	
    
	{
		"title" : "《庄心妍   走着走着就散了》　2014/08/14　其他",
		"url" : "/m/%E5%BA%84%E5%BF%83%E5%A6%8D-%E8%B5%B0%E7%9D%80%E8%B5%B0%E7%9D%80%E5%B0%B1%E6%95%A3%E4%BA%86"
	}
	
	,
	
    
	{
		"title" : "《庄心妍   再见只是陌生人》　2014/08/14　其他",
		"url" : "/m/%E5%BA%84%E5%BF%83%E5%A6%8D-%E5%86%8D%E8%A7%81%E5%8F%AA%E6%98%AF%E9%99%8C%E7%94%9F%E4%BA%BA"
	}
	
	,
	
    
	{
		"title" : "《展展与罗罗   沙漠骆驼》　2014/08/14　其他",
		"url" : "/m/%E5%B1%95%E5%B1%95%E4%B8%8E%E7%BD%97%E7%BD%97-%E6%B2%99%E6%BC%A0%E9%AA%86%E9%A9%BC"
	}
	
	,
	
    
	{
		"title" : "《尹昔眠   奔赴星空》　2014/08/14　其他",
		"url" : "/m/%E5%B0%B9%E6%98%94%E7%9C%A0-%E5%A5%94%E8%B5%B4%E6%98%9F%E7%A9%BA"
	}
	
	,
	
    
	{
		"title" : "《小潘潘（潘柚彤） _ 小峰峰（陈峰）   学猫叫》　2014/08/14　其他",
		"url" : "/m/%E5%B0%8F%E6%BD%98%E6%BD%98-%E6%BD%98%E6%9F%9A%E5%BD%A4-_-%E5%B0%8F%E5%B3%B0%E5%B3%B0-%E9%99%88%E5%B3%B0-%E5%AD%A6%E7%8C%AB%E5%8F%AB"
	}
	
	,
	
    
	{
		"title" : "《宇桐非 _ 胡雯   擦肩而过》　2014/08/14　其他",
		"url" : "/m/%E5%AE%87%E6%A1%90%E9%9D%9E-_-%E8%83%A1%E9%9B%AF-%E6%93%A6%E8%82%A9%E8%80%8C%E8%BF%87"
	}
	
	,
	
    
	{
		"title" : "《孟庭苇   风中有朵雨做的云》　2014/08/14　其他",
		"url" : "/m/%E5%AD%9F%E5%BA%AD%E8%8B%87-%E9%A3%8E%E4%B8%AD%E6%9C%89%E6%9C%B5%E9%9B%A8%E5%81%9A%E7%9A%84%E4%BA%91"
	}
	
	,
	
    
	{
		"title" : "《孙露   离别的秋天》　2014/08/14　其他",
		"url" : "/m/%E5%AD%99%E9%9C%B2-%E7%A6%BB%E5%88%AB%E7%9A%84%E7%A7%8B%E5%A4%A9"
	}
	
	,
	
    
	{
		"title" : "《孙露   爱的可能》　2014/08/14　其他",
		"url" : "/m/%E5%AD%99%E9%9C%B2-%E7%88%B1%E7%9A%84%E5%8F%AF%E8%83%BD"
	}
	
	,
	
    
	{
		"title" : "《孙露   爱上你是一个错》　2014/08/14　其他",
		"url" : "/m/%E5%AD%99%E9%9C%B2-%E7%88%B1%E4%B8%8A%E4%BD%A0%E6%98%AF%E4%B8%80%E4%B8%AA%E9%94%99"
	}
	
	,
	
    
	{
		"title" : "《孙露   把悲伤留给自己》　2014/08/14　其他",
		"url" : "/m/%E5%AD%99%E9%9C%B2-%E6%8A%8A%E6%82%B2%E4%BC%A4%E7%95%99%E7%BB%99%E8%87%AA%E5%B7%B1"
	}
	
	,
	
    
	{
		"title" : "《孙露   小小的太阳》　2014/08/14　其他",
		"url" : "/m/%E5%AD%99%E9%9C%B2-%E5%B0%8F%E5%B0%8F%E7%9A%84%E5%A4%AA%E9%98%B3"
	}
	
	,
	
    
	{
		"title" : "《孙露   再度重相逢》　2014/08/14　其他",
		"url" : "/m/%E5%AD%99%E9%9C%B2-%E5%86%8D%E5%BA%A6%E9%87%8D%E7%9B%B8%E9%80%A2"
	}
	
	,
	
    
	{
		"title" : "《孙露   下辈子也要找到你》　2014/08/14　其他",
		"url" : "/m/%E5%AD%99%E9%9C%B2-%E4%B8%8B%E8%BE%88%E5%AD%90%E4%B9%9F%E8%A6%81%E6%89%BE%E5%88%B0%E4%BD%A0"
	}
	
	,
	
    
	{
		"title" : "《孙语赛 _ 萧全   不仅仅是喜欢》　2014/08/14　其他",
		"url" : "/m/%E5%AD%99%E8%AF%AD%E8%B5%9B-_-%E8%90%A7%E5%85%A8-%E4%B8%8D%E4%BB%85%E4%BB%85%E6%98%AF%E5%96%9C%E6%AC%A2"
	}
	
	,
	
    
	{
		"title" : "《孙耀威   爱的故事上集》　2014/08/14　其他",
		"url" : "/m/%E5%AD%99%E8%80%80%E5%A8%81-%E7%88%B1%E7%9A%84%E6%95%85%E4%BA%8B%E4%B8%8A%E9%9B%86"
	}
	
	,
	
    
	{
		"title" : "《孙燕姿   遇见》　2014/08/14　其他",
		"url" : "/m/%E5%AD%99%E7%87%95%E5%A7%BF-%E9%81%87%E8%A7%81"
	}
	
	,
	
    
	{
		"title" : "《孙燕姿   逆光》　2014/08/14　其他",
		"url" : "/m/%E5%AD%99%E7%87%95%E5%A7%BF-%E9%80%86%E5%85%89"
	}
	
	,
	
    
	{
		"title" : "《孙燕姿   神奇》　2014/08/14　其他",
		"url" : "/m/%E5%AD%99%E7%87%95%E5%A7%BF-%E7%A5%9E%E5%A5%87"
	}
	
	,
	
    
	{
		"title" : "《孙燕姿   我怀念的》　2014/08/14　其他",
		"url" : "/m/%E5%AD%99%E7%87%95%E5%A7%BF-%E6%88%91%E6%80%80%E5%BF%B5%E7%9A%84"
	}
	
	,
	
    
	{
		"title" : "《孙燕姿   开始懂了》　2014/08/14　其他",
		"url" : "/m/%E5%AD%99%E7%87%95%E5%A7%BF-%E5%BC%80%E5%A7%8B%E6%87%82%E4%BA%86"
	}
	
	,
	
    
	{
		"title" : "《孙燕姿   天黑黑》　2014/08/14　其他",
		"url" : "/m/%E5%AD%99%E7%87%95%E5%A7%BF-%E5%A4%A9%E9%BB%91%E9%BB%91"
	}
	
	,
	
    
	{
		"title" : "《孙悦,邰正宵   好人好梦》　2014/08/14　其他",
		"url" : "/m/%E5%AD%99%E6%82%A6,%E9%82%B0%E6%AD%A3%E5%AE%B5-%E5%A5%BD%E4%BA%BA%E5%A5%BD%E6%A2%A6"
	}
	
	,
	
    
	{
		"title" : "《孙子涵   唐人》　2014/08/14　其他",
		"url" : "/m/%E5%AD%99%E5%AD%90%E6%B6%B5-%E5%94%90%E4%BA%BA"
	}
	
	,
	
    
	{
		"title" : "《姚六一   雾里》　2014/08/14　其他",
		"url" : "/m/%E5%A7%9A%E5%85%AD%E4%B8%80-%E9%9B%BE%E9%87%8C"
	}
	
	,
	
    
	{
		"title" : "《大籽   白月光与朱砂痣》　2014/08/14　其他",
		"url" : "/m/%E5%A4%A7%E7%B1%BD-%E7%99%BD%E6%9C%88%E5%85%89%E4%B8%8E%E6%9C%B1%E7%A0%82%E7%97%A3"
	}
	
	,
	
    
	{
		"title" : "《大壮   我们不一样》　2014/08/14　其他",
		"url" : "/m/%E5%A4%A7%E5%A3%AE-%E6%88%91%E4%BB%AC%E4%B8%8D%E4%B8%80%E6%A0%B7"
	}
	
	,
	
    
	{
		"title" : "《大壮   伪装》　2014/08/14　其他",
		"url" : "/m/%E5%A4%A7%E5%A3%AE-%E4%BC%AA%E8%A3%85"
	}
	
	,
	
    
	{
		"title" : "《夏日入侵企画   极恶都市》　2014/08/14　其他",
		"url" : "/m/%E5%A4%8F%E6%97%A5%E5%85%A5%E4%BE%B5%E4%BC%81%E7%94%BB-%E6%9E%81%E6%81%B6%E9%83%BD%E5%B8%82"
	}
	
	,
	
    
	{
		"title" : "《周笔畅   最美的期待》　2014/08/14　其他",
		"url" : "/m/%E5%91%A8%E7%AC%94%E7%95%85-%E6%9C%80%E7%BE%8E%E7%9A%84%E6%9C%9F%E5%BE%85"
	}
	
	,
	
    
	{
		"title" : "《周深   起风了》　2014/08/14　其他",
		"url" : "/m/%E5%91%A8%E6%B7%B1-%E8%B5%B7%E9%A3%8E%E4%BA%86"
	}
	
	,
	
    
	{
		"title" : "《周杰伦、费玉清   千里之外》　2014/08/14　其他",
		"url" : "/m/%E5%91%A8%E6%9D%B0%E4%BC%A6-%E8%B4%B9%E7%8E%89%E6%B8%85-%E5%8D%83%E9%87%8C%E4%B9%8B%E5%A4%96"
	}
	
	,
	
    
	{
		"title" : "《周杰伦 _ 袁咏琳   怎么了》　2014/08/14　其他",
		"url" : "/m/%E5%91%A8%E6%9D%B0%E4%BC%A6-_-%E8%A2%81%E5%92%8F%E7%90%B3-%E6%80%8E%E4%B9%88%E4%BA%86"
	}
	
	,
	
    
	{
		"title" : "《周杰伦   青花瓷》　2014/08/14　其他",
		"url" : "/m/%E5%91%A8%E6%9D%B0%E4%BC%A6-%E9%9D%92%E8%8A%B1%E7%93%B7"
	}
	
	,
	
    
	{
		"title" : "《周杰伦   霍元甲 》　2014/08/14　其他",
		"url" : "/m/%E5%91%A8%E6%9D%B0%E4%BC%A6-%E9%9C%8D%E5%85%83%E7%94%B2"
	}
	
	,
	
    
	{
		"title" : "《周杰伦   蒲公英的约定》　2014/08/14　其他",
		"url" : "/m/%E5%91%A8%E6%9D%B0%E4%BC%A6-%E8%92%B2%E5%85%AC%E8%8B%B1%E7%9A%84%E7%BA%A6%E5%AE%9A"
	}
	
	,
	
    
	{
		"title" : "《周杰伦   菊花台》　2014/08/14　其他",
		"url" : "/m/%E5%91%A8%E6%9D%B0%E4%BC%A6-%E8%8F%8A%E8%8A%B1%E5%8F%B0"
	}
	
	,
	
    
	{
		"title" : "《周杰伦   花海》　2014/08/14　其他",
		"url" : "/m/%E5%91%A8%E6%9D%B0%E4%BC%A6-%E8%8A%B1%E6%B5%B7"
	}
	
	,
	
    
	{
		"title" : "《周杰伦   给我一首歌的时间》　2014/08/14　其他",
		"url" : "/m/%E5%91%A8%E6%9D%B0%E4%BC%A6-%E7%BB%99%E6%88%91%E4%B8%80%E9%A6%96%E6%AD%8C%E7%9A%84%E6%97%B6%E9%97%B4"
	}
	
	,
	
    
	{
		"title" : "《周杰伦   简单爱》　2014/08/14　其他",
		"url" : "/m/%E5%91%A8%E6%9D%B0%E4%BC%A6-%E7%AE%80%E5%8D%95%E7%88%B1"
	}
	
	,
	
    
	{
		"title" : "《周杰伦   稻香》　2014/08/14　其他",
		"url" : "/m/%E5%91%A8%E6%9D%B0%E4%BC%A6-%E7%A8%BB%E9%A6%99"
	}
	
	,
	
    
	{
		"title" : "《周杰伦   爱在西元前》　2014/08/14　其他",
		"url" : "/m/%E5%91%A8%E6%9D%B0%E4%BC%A6-%E7%88%B1%E5%9C%A8%E8%A5%BF%E5%85%83%E5%89%8D"
	}
	
	,
	
    
	{
		"title" : "《周杰伦   本草纲目》　2014/08/14　其他",
		"url" : "/m/%E5%91%A8%E6%9D%B0%E4%BC%A6-%E6%9C%AC%E8%8D%89%E7%BA%B2%E7%9B%AE"
	}
	
	,
	
    
	{
		"title" : "《周杰伦   晴天》　2014/08/14　其他",
		"url" : "/m/%E5%91%A8%E6%9D%B0%E4%BC%A6-%E6%99%B4%E5%A4%A9"
	}
	
	,
	
    
	{
		"title" : "《周杰伦   搁浅》　2014/08/14　其他",
		"url" : "/m/%E5%91%A8%E6%9D%B0%E4%BC%A6-%E6%90%81%E6%B5%85"
	}
	
	,
	
    
	{
		"title" : "《周杰伦   夜的第七章》　2014/08/14　其他",
		"url" : "/m/%E5%91%A8%E6%9D%B0%E4%BC%A6-%E5%A4%9C%E7%9A%84%E7%AC%AC%E4%B8%83%E7%AB%A0"
	}
	
	,
	
    
	{
		"title" : "《周杰伦   夜曲》　2014/08/14　其他",
		"url" : "/m/%E5%91%A8%E6%9D%B0%E4%BC%A6-%E5%A4%9C%E6%9B%B2"
	}
	
	,
	
    
	{
		"title" : "《周杰伦   园游会》　2014/08/14　其他",
		"url" : "/m/%E5%91%A8%E6%9D%B0%E4%BC%A6-%E5%9B%AD%E6%B8%B8%E4%BC%9A"
	}
	
	,
	
    
	{
		"title" : "《周杰伦   告白气球》　2014/08/14　其他",
		"url" : "/m/%E5%91%A8%E6%9D%B0%E4%BC%A6-%E5%91%8A%E7%99%BD%E6%B0%94%E7%90%83"
	}
	
	,
	
    
	{
		"title" : "《周杰伦   听妈妈的话》　2014/08/14　其他",
		"url" : "/m/%E5%91%A8%E6%9D%B0%E4%BC%A6-%E5%90%AC%E5%A6%88%E5%A6%88%E7%9A%84%E8%AF%9D"
	}
	
	,
	
    
	{
		"title" : "《周杰伦   发如雪》　2014/08/14　其他",
		"url" : "/m/%E5%91%A8%E6%9D%B0%E4%BC%A6-%E5%8F%91%E5%A6%82%E9%9B%AA"
	}
	
	,
	
    
	{
		"title" : "《周杰伦   双截棍》　2014/08/14　其他",
		"url" : "/m/%E5%91%A8%E6%9D%B0%E4%BC%A6-%E5%8F%8C%E6%88%AA%E6%A3%8D"
	}
	
	,
	
    
	{
		"title" : "《周杰伦   半岛铁盒》　2014/08/14　其他",
		"url" : "/m/%E5%91%A8%E6%9D%B0%E4%BC%A6-%E5%8D%8A%E5%B2%9B%E9%93%81%E7%9B%92"
	}
	
	,
	
    
	{
		"title" : "《周杰伦   兰亭序》　2014/08/14　其他",
		"url" : "/m/%E5%91%A8%E6%9D%B0%E4%BC%A6-%E5%85%B0%E4%BA%AD%E5%BA%8F"
	}
	
	,
	
    
	{
		"title" : "《周杰伦   以父之名》　2014/08/14　其他",
		"url" : "/m/%E5%91%A8%E6%9D%B0%E4%BC%A6-%E4%BB%A5%E7%88%B6%E4%B9%8B%E5%90%8D"
	}
	
	,
	
    
	{
		"title" : "《周杰伦   东风破》　2014/08/14　其他",
		"url" : "/m/%E5%91%A8%E6%9D%B0%E4%BC%A6-%E4%B8%9C%E9%A3%8E%E7%A0%B4"
	}
	
	,
	
    
	{
		"title" : "《周杰伦   不能说的秘密》　2014/08/14　其他",
		"url" : "/m/%E5%91%A8%E6%9D%B0%E4%BC%A6-%E4%B8%8D%E8%83%BD%E8%AF%B4%E7%9A%84%E7%A7%98%E5%AF%86"
	}
	
	,
	
    
	{
		"title" : "《周杰伦   七里香》　2014/08/14　其他",
		"url" : "/m/%E5%91%A8%E6%9D%B0%E4%BC%A6-%E4%B8%83%E9%87%8C%E9%A6%99"
	}
	
	,
	
    
	{
		"title" : "《周杰伦   mojito》　2014/08/14　其他",
		"url" : "/m/%E5%91%A8%E6%9D%B0%E4%BC%A6-Mojito"
	}
	
	,
	
    
	{
		"title" : "《周慧敏   痴心换情深》　2014/08/14　其他",
		"url" : "/m/%E5%91%A8%E6%85%A7%E6%95%8F-%E7%97%B4%E5%BF%83%E6%8D%A2%E6%83%85%E6%B7%B1"
	}
	
	,
	
    
	{
		"title" : "《周思涵   过客》　2014/08/14　其他",
		"url" : "/m/%E5%91%A8%E6%80%9D%E6%B6%B5-%E8%BF%87%E5%AE%A2"
	}
	
	,
	
    
	{
		"title" : "《周思涵   走不出来》　2014/08/14　其他",
		"url" : "/m/%E5%91%A8%E6%80%9D%E6%B6%B5-%E8%B5%B0%E4%B8%8D%E5%87%BA%E6%9D%A5"
	}
	
	,
	
    
	{
		"title" : "《周思涵   散了吧》　2014/08/14　其他",
		"url" : "/m/%E5%91%A8%E6%80%9D%E6%B6%B5-%E6%95%A3%E4%BA%86%E5%90%A7"
	}
	
	,
	
    
	{
		"title" : "《周思涵   失眠》　2014/08/14　其他",
		"url" : "/m/%E5%91%A8%E6%80%9D%E6%B6%B5-%E5%A4%B1%E7%9C%A0"
	}
	
	,
	
    
	{
		"title" : "《周思涵   备爱》　2014/08/14　其他",
		"url" : "/m/%E5%91%A8%E6%80%9D%E6%B6%B5-%E5%A4%87%E7%88%B1"
	}
	
	,
	
    
	{
		"title" : "《周华健 _ 齐豫   天下有情人》　2014/08/14　其他",
		"url" : "/m/%E5%91%A8%E5%8D%8E%E5%81%A5-_-%E9%BD%90%E8%B1%AB-%E5%A4%A9%E4%B8%8B%E6%9C%89%E6%83%85%E4%BA%BA"
	}
	
	,
	
    
	{
		"title" : "《周华健   风雨无阻》　2014/08/14　其他",
		"url" : "/m/%E5%91%A8%E5%8D%8E%E5%81%A5-%E9%A3%8E%E9%9B%A8%E6%97%A0%E9%98%BB"
	}
	
	,
	
    
	{
		"title" : "《周华健   难念的经》　2014/08/14　其他",
		"url" : "/m/%E5%91%A8%E5%8D%8E%E5%81%A5-%E9%9A%BE%E5%BF%B5%E7%9A%84%E7%BB%8F"
	}
	
	,
	
    
	{
		"title" : "《周华健   让我欢喜让我忧》　2014/08/14　其他",
		"url" : "/m/%E5%91%A8%E5%8D%8E%E5%81%A5-%E8%AE%A9%E6%88%91%E6%AC%A2%E5%96%9C%E8%AE%A9%E6%88%91%E5%BF%A7"
	}
	
	,
	
    
	{
		"title" : "《周华健   花心》　2014/08/14　其他",
		"url" : "/m/%E5%91%A8%E5%8D%8E%E5%81%A5-%E8%8A%B1%E5%BF%83"
	}
	
	,
	
    
	{
		"title" : "《周华健   有没有一首歌会让你想起我》　2014/08/14　其他",
		"url" : "/m/%E5%91%A8%E5%8D%8E%E5%81%A5-%E6%9C%89%E6%B2%A1%E6%9C%89%E4%B8%80%E9%A6%96%E6%AD%8C%E4%BC%9A%E8%AE%A9%E4%BD%A0%E6%83%B3%E8%B5%B7%E6%88%91"
	}
	
	,
	
    
	{
		"title" : "《周华健   刀剑如梦》　2014/08/14　其他",
		"url" : "/m/%E5%91%A8%E5%8D%8E%E5%81%A5-%E5%88%80%E5%89%91%E5%A6%82%E6%A2%A6"
	}
	
	,
	
    
	{
		"title" : "《周传雄   黄昏》　2014/08/14　其他",
		"url" : "/m/%E5%91%A8%E4%BC%A0%E9%9B%84-%E9%BB%84%E6%98%8F"
	}
	
	,
	
    
	{
		"title" : "《周传雄   青花》　2014/08/14　其他",
		"url" : "/m/%E5%91%A8%E4%BC%A0%E9%9B%84-%E9%9D%92%E8%8A%B1"
	}
	
	,
	
    
	{
		"title" : "《周传雄   蓝色土耳其》　2014/08/14　其他",
		"url" : "/m/%E5%91%A8%E4%BC%A0%E9%9B%84-%E8%93%9D%E8%89%B2%E5%9C%9F%E8%80%B3%E5%85%B6"
	}
	
	,
	
    
	{
		"title" : "《周传雄   男人海洋》　2014/08/14　其他",
		"url" : "/m/%E5%91%A8%E4%BC%A0%E9%9B%84-%E7%94%B7%E4%BA%BA%E6%B5%B7%E6%B4%8B"
	}
	
	,
	
    
	{
		"title" : "《周传雄   寂寞沙洲冷》　2014/08/14　其他",
		"url" : "/m/%E5%91%A8%E4%BC%A0%E9%9B%84-%E5%AF%82%E5%AF%9E%E6%B2%99%E6%B4%B2%E5%86%B7"
	}
	
	,
	
    
	{
		"title" : "《周传雄   冬天的秘密》　2014/08/14　其他",
		"url" : "/m/%E5%91%A8%E4%BC%A0%E9%9B%84-%E5%86%AC%E5%A4%A9%E7%9A%84%E7%A7%98%E5%AF%86"
	}
	
	,
	
    
	{
		"title" : "《周传雄   关不上的窗》　2014/08/14　其他",
		"url" : "/m/%E5%91%A8%E4%BC%A0%E9%9B%84-%E5%85%B3%E4%B8%8D%E4%B8%8A%E7%9A%84%E7%AA%97"
	}
	
	,
	
    
	{
		"title" : "《吴青峰   起风了》　2014/08/14　其他",
		"url" : "/m/%E5%90%B4%E9%9D%92%E5%B3%B0-%E8%B5%B7%E9%A3%8E%E4%BA%86"
	}
	
	,
	
    
	{
		"title" : "《吴雨霏   生生世世爱》　2014/08/14　其他",
		"url" : "/m/%E5%90%B4%E9%9B%A8%E9%9C%8F-%E7%94%9F%E7%94%9F%E4%B8%96%E4%B8%96%E7%88%B1"
	}
	
	,
	
    
	{
		"title" : "《吴奇隆   转弯》　2014/08/14　其他",
		"url" : "/m/%E5%90%B4%E5%A5%87%E9%9A%86-%E8%BD%AC%E5%BC%AF"
	}
	
	,
	
    
	{
		"title" : "《吴奇隆   烟火》　2014/08/14　其他",
		"url" : "/m/%E5%90%B4%E5%A5%87%E9%9A%86-%E7%83%9F%E7%81%AB"
	}
	
	,
	
    
	{
		"title" : "《吴克群   星辰变》　2014/08/14　其他",
		"url" : "/m/%E5%90%B4%E5%85%8B%E7%BE%A4-%E6%98%9F%E8%BE%B0%E5%8F%98"
	}
	
	,
	
    
	{
		"title" : "《司南   冬眠》　2014/08/14　其他",
		"url" : "/m/%E5%8F%B8%E5%8D%97-%E5%86%AC%E7%9C%A0"
	}
	
	,
	
    
	{
		"title" : "《叶炫清   九张机》　2014/08/14　其他",
		"url" : "/m/%E5%8F%B6%E7%82%AB%E6%B8%85-%E4%B9%9D%E5%BC%A0%E6%9C%BA"
	}
	
	,
	
    
	{
		"title" : "《南宫嘉骏 _ 姜玉阳   回忆总想哭》　2014/08/14　其他",
		"url" : "/m/%E5%8D%97%E5%AE%AB%E5%98%89%E9%AA%8F-_-%E5%A7%9C%E7%8E%89%E9%98%B3-%E5%9B%9E%E5%BF%86%E6%80%BB%E6%83%B3%E5%93%AD"
	}
	
	,
	
    
	{
		"title" : "《华莎 (화사)   마리아 (maria)》　2014/08/14　其他",
		"url" : "/m/%E5%8D%8E%E8%8E%8E-(%E1%84%92%E1%85%AA%E1%84%89%E1%85%A1)-%E1%84%86%E1%85%A1%E1%84%85%E1%85%B5%E1%84%8B%E1%85%A1-(Maria)"
	}
	
	,
	
    
	{
		"title" : "《华晨宇   齐天大圣》　2014/08/14　其他",
		"url" : "/m/%E5%8D%8E%E6%99%A8%E5%AE%87-%E9%BD%90%E5%A4%A9%E5%A4%A7%E5%9C%A3"
	}
	
	,
	
    
	{
		"title" : "《华晨宇   烟火里的尘埃》　2014/08/14　其他",
		"url" : "/m/%E5%8D%8E%E6%99%A8%E5%AE%87-%E7%83%9F%E7%81%AB%E9%87%8C%E7%9A%84%E5%B0%98%E5%9F%83"
	}
	
	,
	
    
	{
		"title" : "《半阳   流浪》　2014/08/14　其他",
		"url" : "/m/%E5%8D%8A%E9%98%B3-%E6%B5%81%E6%B5%AA"
	}
	
	,
	
    
	{
		"title" : "《半阳   一曲相思》　2014/08/14　其他",
		"url" : "/m/%E5%8D%8A%E9%98%B3-%E4%B8%80%E6%9B%B2%E7%9B%B8%E6%80%9D"
	}
	
	,
	
    
	{
		"title" : "《刘至佳 _ 韩瞳   时光背面的我》　2014/08/14　其他",
		"url" : "/m/%E5%88%98%E8%87%B3%E4%BD%B3-_-%E9%9F%A9%E7%9E%B3-%E6%97%B6%E5%85%89%E8%83%8C%E9%9D%A2%E7%9A%84%E6%88%91"
	}
	
	,
	
    
	{
		"title" : "《刘珂矣   风筝误》　2014/08/14　其他",
		"url" : "/m/%E5%88%98%E7%8F%82%E7%9F%A3-%E9%A3%8E%E7%AD%9D%E8%AF%AF"
	}
	
	,
	
    
	{
		"title" : "《刘珂矣   芙蓉雨》　2014/08/14　其他",
		"url" : "/m/%E5%88%98%E7%8F%82%E7%9F%A3-%E8%8A%99%E8%93%89%E9%9B%A8"
	}
	
	,
	
    
	{
		"title" : "《刘珂矣   半壶纱》　2014/08/14　其他",
		"url" : "/m/%E5%88%98%E7%8F%82%E7%9F%A3-%E5%8D%8A%E5%A3%B6%E7%BA%B1"
	}
	
	,
	
    
	{
		"title" : "《刘明湘   漂洋过海来看你》　2014/08/14　其他",
		"url" : "/m/%E5%88%98%E6%98%8E%E6%B9%98-%E6%BC%82%E6%B4%8B%E8%BF%87%E6%B5%B7%E6%9D%A5%E7%9C%8B%E4%BD%A0"
	}
	
	,
	
    
	{
		"title" : "《刘惜君 _ 王赫野   大风吹 (live)》　2014/08/14　其他",
		"url" : "/m/%E5%88%98%E6%83%9C%E5%90%9B-_-%E7%8E%8B%E8%B5%AB%E9%87%8E-%E5%A4%A7%E9%A3%8E%E5%90%B9-(Live)"
	}
	
	,
	
    
	{
		"title" : "《刘德华、柯受良、吴宗宪   笨小孩》　2014/08/14　其他",
		"url" : "/m/%E5%88%98%E5%BE%B7%E5%8D%8E-%E6%9F%AF%E5%8F%97%E8%89%AF-%E5%90%B4%E5%AE%97%E5%AE%AA-%E7%AC%A8%E5%B0%8F%E5%AD%A9"
	}
	
	,
	
    
	{
		"title" : "《刘德华   谢谢你的爱》　2014/08/14　其他",
		"url" : "/m/%E5%88%98%E5%BE%B7%E5%8D%8E-%E8%B0%A2%E8%B0%A2%E4%BD%A0%E7%9A%84%E7%88%B1"
	}
	
	,
	
    
	{
		"title" : "《刘德华   练习》　2014/08/14　其他",
		"url" : "/m/%E5%88%98%E5%BE%B7%E5%8D%8E-%E7%BB%83%E4%B9%A0"
	}
	
	,
	
    
	{
		"title" : "《刘德华   男人哭吧不是罪》　2014/08/14　其他",
		"url" : "/m/%E5%88%98%E5%BE%B7%E5%8D%8E-%E7%94%B7%E4%BA%BA%E5%93%AD%E5%90%A7%E4%B8%8D%E6%98%AF%E7%BD%AA"
	}
	
	,
	
    
	{
		"title" : "《刘德华   独自去偷欢》　2014/08/14　其他",
		"url" : "/m/%E5%88%98%E5%BE%B7%E5%8D%8E-%E7%8B%AC%E8%87%AA%E5%8E%BB%E5%81%B7%E6%AC%A2"
	}
	
	,
	
    
	{
		"title" : "《刘德华   爱你一万年》　2014/08/14　其他",
		"url" : "/m/%E5%88%98%E5%BE%B7%E5%8D%8E-%E7%88%B1%E4%BD%A0%E4%B8%80%E4%B8%87%E5%B9%B4"
	}
	
	,
	
    
	{
		"title" : "《刘德华   暗里着迷》　2014/08/14　其他",
		"url" : "/m/%E5%88%98%E5%BE%B7%E5%8D%8E-%E6%9A%97%E9%87%8C%E7%9D%80%E8%BF%B7"
	}
	
	,
	
    
	{
		"title" : "《刘德华   我恨我痴心》　2014/08/14　其他",
		"url" : "/m/%E5%88%98%E5%BE%B7%E5%8D%8E-%E6%88%91%E6%81%A8%E6%88%91%E7%97%B4%E5%BF%83"
	}
	
	,
	
    
	{
		"title" : "《刘德华   情感的禁区》　2014/08/14　其他",
		"url" : "/m/%E5%88%98%E5%BE%B7%E5%8D%8E-%E6%83%85%E6%84%9F%E7%9A%84%E7%A6%81%E5%8C%BA"
	}
	
	,
	
    
	{
		"title" : "《刘德华   恭喜发财》　2014/08/14　其他",
		"url" : "/m/%E5%88%98%E5%BE%B7%E5%8D%8E-%E6%81%AD%E5%96%9C%E5%8F%91%E8%B4%A2"
	}
	
	,
	
    
	{
		"title" : "《刘德华   忘情水》　2014/08/14　其他",
		"url" : "/m/%E5%88%98%E5%BE%B7%E5%8D%8E-%E5%BF%98%E6%83%85%E6%B0%B4"
	}
	
	,
	
    
	{
		"title" : "《刘德华   开心的马骝》　2014/08/14　其他",
		"url" : "/m/%E5%88%98%E5%BE%B7%E5%8D%8E-%E5%BC%80%E5%BF%83%E7%9A%84%E9%A9%AC%E9%AA%9D"
	}
	
	,
	
    
	{
		"title" : "《刘德华   天意》　2014/08/14　其他",
		"url" : "/m/%E5%88%98%E5%BE%B7%E5%8D%8E-%E5%A4%A9%E6%84%8F"
	}
	
	,
	
    
	{
		"title" : "《刘德华   冰雨》　2014/08/14　其他",
		"url" : "/m/%E5%88%98%E5%BE%B7%E5%8D%8E-%E5%86%B0%E9%9B%A8"
	}
	
	,
	
    
	{
		"title" : "《刘德华   今天》　2014/08/14　其他",
		"url" : "/m/%E5%88%98%E5%BE%B7%E5%8D%8E-%E4%BB%8A%E5%A4%A9"
	}
	
	,
	
    
	{
		"title" : "《刘德华   中国人》　2014/08/14　其他",
		"url" : "/m/%E5%88%98%E5%BE%B7%E5%8D%8E-%E4%B8%AD%E5%9B%BD%E4%BA%BA"
	}
	
	,
	
    
	{
		"title" : "《刘德华   世界第一等》　2014/08/14　其他",
		"url" : "/m/%E5%88%98%E5%BE%B7%E5%8D%8E-%E4%B8%96%E7%95%8C%E7%AC%AC%E4%B8%80%E7%AD%89"
	}
	
	,
	
    
	{
		"title" : "《刘德华   一起走过的日子》　2014/08/14　其他",
		"url" : "/m/%E5%88%98%E5%BE%B7%E5%8D%8E-%E4%B8%80%E8%B5%B7%E8%B5%B0%E8%BF%87%E7%9A%84%E6%97%A5%E5%AD%90"
	}
	
	,
	
    
	{
		"title" : "《刘德华   17岁》　2014/08/14　其他",
		"url" : "/m/%E5%88%98%E5%BE%B7%E5%8D%8E-17%E5%B2%81"
	}
	
	,
	
    
	{
		"title" : "《刘刚   怀念青春》　2014/08/14　其他",
		"url" : "/m/%E5%88%98%E5%88%9A-%E6%80%80%E5%BF%B5%E9%9D%92%E6%98%A5"
	}
	
	,
	
    
	{
		"title" : "《刀郎   西海情歌》　2014/08/14　其他",
		"url" : "/m/%E5%88%80%E9%83%8E-%E8%A5%BF%E6%B5%B7%E6%83%85%E6%AD%8C"
	}
	
	,
	
    
	{
		"title" : "《凤凰传奇   海底（live）》　2014/08/14　其他",
		"url" : "/m/%E5%87%A4%E5%87%B0%E4%BC%A0%E5%A5%87-%E6%B5%B7%E5%BA%95-Live"
	}
	
	,
	
    
	{
		"title" : "《凤凰传奇   奢香夫人》　2014/08/14　其他",
		"url" : "/m/%E5%87%A4%E5%87%B0%E4%BC%A0%E5%A5%87-%E5%A5%A2%E9%A6%99%E5%A4%AB%E4%BA%BA"
	}
	
	,
	
    
	{
		"title" : "《凤凰传奇   奇迹世界》　2014/08/14　其他",
		"url" : "/m/%E5%87%A4%E5%87%B0%E4%BC%A0%E5%A5%87-%E5%A5%87%E8%BF%B9%E4%B8%96%E7%95%8C"
	}
	
	,
	
    
	{
		"title" : "《冯提莫   佛系少女》　2014/08/14　其他",
		"url" : "/m/%E5%86%AF%E6%8F%90%E8%8E%AB-%E4%BD%9B%E7%B3%BB%E5%B0%91%E5%A5%B3"
	}
	
	,
	
    
	{
		"title" : "《关心   提笔忘情》　2014/08/14　其他",
		"url" : "/m/%E5%85%B3%E5%BF%83-%E6%8F%90%E7%AC%94%E5%BF%98%E6%83%85"
	}
	
	,
	
    
	{
		"title" : "《兰雨   最后一次的温柔》　2014/08/14　其他",
		"url" : "/m/%E5%85%B0%E9%9B%A8-%E6%9C%80%E5%90%8E%E4%B8%80%E6%AC%A1%E7%9A%84%E6%B8%A9%E6%9F%94"
	}
	
	,
	
    
	{
		"title" : "《傅如乔   微微》　2014/08/14　其他",
		"url" : "/m/%E5%82%85%E5%A6%82%E4%B9%94-%E5%BE%AE%E5%BE%AE"
	}
	
	,
	
    
	{
		"title" : "《你的上好佳   白鸽》　2014/08/14　其他",
		"url" : "/m/%E4%BD%A0%E7%9A%84%E4%B8%8A%E5%A5%BD%E4%BD%B3-%E7%99%BD%E9%B8%BD"
	}
	
	,
	
    
	{
		"title" : "《伍佰   突然的自我》　2014/08/14　其他",
		"url" : "/m/%E4%BC%8D%E4%BD%B0-%E7%AA%81%E7%84%B6%E7%9A%84%E8%87%AA%E6%88%91"
	}
	
	,
	
    
	{
		"title" : "《伍佰   挪威的森林》　2014/08/14　其他",
		"url" : "/m/%E4%BC%8D%E4%BD%B0-%E6%8C%AA%E5%A8%81%E7%9A%84%E6%A3%AE%E6%9E%97"
	}
	
	,
	
    
	{
		"title" : "《伊格赛听 _ 叶里   谪仙》　2014/08/14　其他",
		"url" : "/m/%E4%BC%8A%E6%A0%BC%E8%B5%9B%E5%90%AC-_-%E5%8F%B6%E9%87%8C-%E8%B0%AA%E4%BB%99"
	}
	
	,
	
    
	{
		"title" : "《任贤齐 杨千嬅   花好月圆夜》　2014/08/14　其他",
		"url" : "/m/%E4%BB%BB%E8%B4%A4%E9%BD%90-%E6%9D%A8%E5%8D%83%E5%AC%85-%E8%8A%B1%E5%A5%BD%E6%9C%88%E5%9C%86%E5%A4%9C"
	}
	
	,
	
    
	{
		"title" : "《任然   飞鸟和蝉》　2014/08/14　其他",
		"url" : "/m/%E4%BB%BB%E7%84%B6-%E9%A3%9E%E9%B8%9F%E5%92%8C%E8%9D%89"
	}
	
	,
	
    
	{
		"title" : "《任然   空空如也》　2014/08/14　其他",
		"url" : "/m/%E4%BB%BB%E7%84%B6-%E7%A9%BA%E7%A9%BA%E5%A6%82%E4%B9%9F"
	}
	
	,
	
    
	{
		"title" : "《任然   无人之岛》　2014/08/14　其他",
		"url" : "/m/%E4%BB%BB%E7%84%B6-%E6%97%A0%E4%BA%BA%E4%B9%8B%E5%B2%9B"
	}
	
	,
	
    
	{
		"title" : "《任然   山外小楼夜听雨》　2014/08/14　其他",
		"url" : "/m/%E4%BB%BB%E7%84%B6-%E5%B1%B1%E5%A4%96%E5%B0%8F%E6%A5%BC%E5%A4%9C%E5%90%AC%E9%9B%A8"
	}
	
	,
	
    
	{
		"title" : "《任然   后继者》　2014/08/14　其他",
		"url" : "/m/%E4%BB%BB%E7%84%B6-%E5%90%8E%E7%BB%A7%E8%80%85"
	}
	
	,
	
    
	{
		"title" : "《任然   凉城》　2014/08/14　其他",
		"url" : "/m/%E4%BB%BB%E7%84%B6-%E5%87%89%E5%9F%8E"
	}
	
	,
	
    
	{
		"title" : "《任然   一去不回的时光》　2014/08/14　其他",
		"url" : "/m/%E4%BB%BB%E7%84%B6-%E4%B8%80%E5%8E%BB%E4%B8%8D%E5%9B%9E%E7%9A%84%E6%97%B6%E5%85%89"
	}
	
	,
	
    
	{
		"title" : "《付雪   金玉良缘》　2014/08/14　其他",
		"url" : "/m/%E4%BB%98%E9%9B%AA-%E9%87%91%E7%8E%89%E8%89%AF%E7%BC%98"
	}
	
	,
	
    
	{
		"title" : "《亦伊   归来是故乡》　2014/08/14　其他",
		"url" : "/m/%E4%BA%A6%E4%BC%8A-%E5%BD%92%E6%9D%A5%E6%98%AF%E6%95%85%E4%B9%A1"
	}
	
	,
	
    
	{
		"title" : "《五月天   倔强》　2014/08/14　其他",
		"url" : "/m/%E4%BA%94%E6%9C%88%E5%A4%A9-%E5%80%94%E5%BC%BA"
	}
	
	,
	
    
	{
		"title" : "《云朵   我的楼兰》　2014/08/14　其他",
		"url" : "/m/%E4%BA%91%E6%9C%B5-%E6%88%91%E7%9A%84%E6%A5%BC%E5%85%B0"
	}
	
	,
	
    
	{
		"title" : "《云朵   倔强》　2014/08/14　其他",
		"url" : "/m/%E4%BA%91%E6%9C%B5-%E5%80%94%E5%BC%BA"
	}
	
	,
	
    
	{
		"title" : "《于文文   体面》　2014/08/14　其他",
		"url" : "/m/%E4%BA%8E%E6%96%87%E6%96%87-%E4%BD%93%E9%9D%A2"
	}
	
	,
	
    
	{
		"title" : "《于博雅   太迟》　2014/08/14　其他",
		"url" : "/m/%E4%BA%8E%E5%8D%9A%E9%9B%85-%E5%A4%AA%E8%BF%9F"
	}
	
	,
	
    
	{
		"title" : "《买辣椒也用券   起风了》　2014/08/14　其他",
		"url" : "/m/%E4%B9%B0%E8%BE%A3%E6%A4%92%E4%B9%9F%E7%94%A8%E5%88%B8-%E8%B5%B7%E9%A3%8E%E4%BA%86"
	}
	
	,
	
    
	{
		"title" : "《不够   收敛》　2014/08/14　其他",
		"url" : "/m/%E4%B8%8D%E5%A4%9F-%E6%94%B6%E6%95%9B"
	}
	
	,
	
    
	{
		"title" : "《七朵组合   青蛇》　2014/08/14　其他",
		"url" : "/m/%E4%B8%83%E6%9C%B5%E7%BB%84%E5%90%88-%E9%9D%92%E8%9B%87"
	}
	
	,
	
    
	{
		"title" : "《七朵组合   醉花荫》　2014/08/14　其他",
		"url" : "/m/%E4%B8%83%E6%9C%B5%E7%BB%84%E5%90%88-%E9%86%89%E8%8A%B1%E8%8D%AB"
	}
	
	,
	
    
	{
		"title" : "《七朵组合   落花情》　2014/08/14　其他",
		"url" : "/m/%E4%B8%83%E6%9C%B5%E7%BB%84%E5%90%88-%E8%90%BD%E8%8A%B1%E6%83%85"
	}
	
	,
	
    
	{
		"title" : "《七朵组合   玉生烟》　2014/08/14　其他",
		"url" : "/m/%E4%B8%83%E6%9C%B5%E7%BB%84%E5%90%88-%E7%8E%89%E7%94%9F%E7%83%9F"
	}
	
	,
	
    
	{
		"title" : "《七朵组合   咏春》　2014/08/14　其他",
		"url" : "/m/%E4%B8%83%E6%9C%B5%E7%BB%84%E5%90%88-%E5%92%8F%E6%98%A5"
	}
	
	,
	
    
	{
		"title" : "《丁当   猜不透》　2014/08/14　其他",
		"url" : "/m/%E4%B8%81%E5%BD%93-%E7%8C%9C%E4%B8%8D%E9%80%8F"
	}
	
	,
	
    
	{
		"title" : "《一支榴莲   海底》　2014/08/14　其他",
		"url" : "/m/%E4%B8%80%E6%94%AF%E6%A6%B4%E8%8E%B2-%E6%B5%B7%E5%BA%95"
	}
	
	,
	
    
	{
		"title" : "《M_o_v_e   rage your dream》　2014/08/14　其他",
		"url" : "/m/m_o_v_e-Rage-your-dream"
	}
	
	,
	
    
	{
		"title" : "《En   嚣张》　2014/08/14　其他",
		"url" : "/m/en-%E5%9A%A3%E5%BC%A0"
	}
	
	,
	
    
	{
		"title" : "《Zic子晨   我要找到你》　2014/08/14　其他",
		"url" : "/m/Zic%E5%AD%90%E6%99%A8-%E6%88%91%E8%A6%81%E6%89%BE%E5%88%B0%E4%BD%A0"
	}
	
	,
	
    
	{
		"title" : "《Vicetone _ cozi zuehlsdorff   nevada》　2014/08/14　其他",
		"url" : "/m/Vicetone-_-Cozi-Zuehlsdorff-Nevada"
	}
	
	,
	
    
	{
		"title" : "《Uu   那女孩对我说》　2014/08/14　其他",
		"url" : "/m/Uu-%E9%82%A3%E5%A5%B3%E5%AD%A9%E5%AF%B9%E6%88%91%E8%AF%B4"
	}
	
	,
	
    
	{
		"title" : "《Uu   夏天的风》　2014/08/14　其他",
		"url" : "/m/Uu-%E5%A4%8F%E5%A4%A9%E7%9A%84%E9%A3%8E"
	}
	
	,
	
    
	{
		"title" : "《Twins   莫斯科没有眼泪》　2014/08/14　其他",
		"url" : "/m/Twins-%E8%8E%AB%E6%96%AF%E7%A7%91%E6%B2%A1%E6%9C%89%E7%9C%BC%E6%B3%AA"
	}
	
	,
	
    
	{
		"title" : "《Twins   死性不改》　2014/08/14　其他",
		"url" : "/m/Twins-%E6%AD%BB%E6%80%A7%E4%B8%8D%E6%94%B9"
	}
	
	,
	
    
	{
		"title" : "《Twins   星光游乐园》　2014/08/14　其他",
		"url" : "/m/Twins-%E6%98%9F%E5%85%89%E6%B8%B8%E4%B9%90%E5%9B%AD"
	}
	
	,
	
    
	{
		"title" : "《The chainsmokers _ coldplay   something just like this》　2014/08/14　其他",
		"url" : "/m/The-Chainsmokers-_-Coldplay-Something-Just-Like-This"
	}
	
	,
	
    
	{
		"title" : "《Taylor swift   we are never ever getting back together》　2014/08/14　其他",
		"url" : "/m/Taylor-Swift-We-Are-Never-Ever-Getting-Back-Together"
	}
	
	,
	
    
	{
		"title" : "《Taylor swift   shake it off》　2014/08/14　其他",
		"url" : "/m/Taylor-Swift-Shake-It-Off"
	}
	
	,
	
    
	{
		"title" : "《Taylor swift   red》　2014/08/14　其他",
		"url" : "/m/Taylor-Swift-Red"
	}
	
	,
	
    
	{
		"title" : "《Taylor swift   love story》　2014/08/14　其他",
		"url" : "/m/Taylor-Swift-Love-Story"
	}
	
	,
	
    
	{
		"title" : "《Taylor swift   i knew you were trouble_》　2014/08/14　其他",
		"url" : "/m/Taylor-Swift-I-Knew-You-Were-Trouble_"
	}
	
	,
	
    
	{
		"title" : "《S.h.e   魔力》　2014/08/14　其他",
		"url" : "/m/S.H.E-%E9%AD%94%E5%8A%9B"
	}
	
	,
	
    
	{
		"title" : "《S.h.e   迫不及待》　2014/08/14　其他",
		"url" : "/m/S.H.E-%E8%BF%AB%E4%B8%8D%E5%8F%8A%E5%BE%85"
	}
	
	,
	
    
	{
		"title" : "《S.h.e   触电》　2014/08/14　其他",
		"url" : "/m/S.H.E-%E8%A7%A6%E7%94%B5"
	}
	
	,
	
    
	{
		"title" : "《S.h.e   花都开好了》　2014/08/14　其他",
		"url" : "/m/S.H.E-%E8%8A%B1%E9%83%BD%E5%BC%80%E5%A5%BD%E4%BA%86"
	}
	
	,
	
    
	{
		"title" : "《S.h.e   花又开好了》　2014/08/14　其他",
		"url" : "/m/S.H.E-%E8%8A%B1%E5%8F%88%E5%BC%80%E5%A5%BD%E4%BA%86"
	}
	
	,
	
    
	{
		"title" : "《S.h.e   美丽新世界》　2014/08/14　其他",
		"url" : "/m/S.H.E-%E7%BE%8E%E4%B8%BD%E6%96%B0%E4%B8%96%E7%95%8C"
	}
	
	,
	
    
	{
		"title" : "《S.h.e   紫藤花》　2014/08/14　其他",
		"url" : "/m/S.H.E-%E7%B4%AB%E8%97%A4%E8%8A%B1"
	}
	
	,
	
    
	{
		"title" : "《S.h.e   离开地球表面》　2014/08/14　其他",
		"url" : "/m/S.H.E-%E7%A6%BB%E5%BC%80%E5%9C%B0%E7%90%83%E8%A1%A8%E9%9D%A2"
	}
	
	,
	
    
	{
		"title" : "《S.h.e   痛快》　2014/08/14　其他",
		"url" : "/m/S.H.E-%E7%97%9B%E5%BF%AB"
	}
	
	,
	
    
	{
		"title" : "《S.h.e   爱上你》　2014/08/14　其他",
		"url" : "/m/S.H.E-%E7%88%B1%E4%B8%8A%E4%BD%A0"
	}
	
	,
	
    
	{
		"title" : "《S.h.e   热带雨林》　2014/08/14　其他",
		"url" : "/m/S.H.E-%E7%83%AD%E5%B8%A6%E9%9B%A8%E6%9E%97"
	}
	
	,
	
    
	{
		"title" : "《S.h.e   波斯猫》　2014/08/14　其他",
		"url" : "/m/S.H.E-%E6%B3%A2%E6%96%AF%E7%8C%AB"
	}
	
	,
	
    
	{
		"title" : "《S.h.e   星光》　2014/08/14　其他",
		"url" : "/m/S.H.E-%E6%98%9F%E5%85%89"
	}
	
	,
	
    
	{
		"title" : "《S.h.e   恋人未满》　2014/08/14　其他",
		"url" : "/m/S.H.E-%E6%81%8B%E4%BA%BA%E6%9C%AA%E6%BB%A1"
	}
	
	,
	
    
	{
		"title" : "《S.h.e   安静了》　2014/08/14　其他",
		"url" : "/m/S.H.E-%E5%AE%89%E9%9D%99%E4%BA%86"
	}
	
	,
	
    
	{
		"title" : "《S.h.e   天灰》　2014/08/14　其他",
		"url" : "/m/S.H.E-%E5%A4%A9%E7%81%B0"
	}
	
	,
	
    
	{
		"title" : "《S.h.e   天亮了》　2014/08/14　其他",
		"url" : "/m/S.H.E-%E5%A4%A9%E4%BA%AE%E4%BA%86"
	}
	
	,
	
    
	{
		"title" : "《S.h.e   听袁惟仁弹吉他》　2014/08/14　其他",
		"url" : "/m/S.H.E-%E5%90%AC%E8%A2%81%E6%83%9F%E4%BB%81%E5%BC%B9%E5%90%89%E4%BB%96"
	}
	
	,
	
    
	{
		"title" : "《S.h.e   半糖主义》　2014/08/14　其他",
		"url" : "/m/S.H.E-%E5%8D%8A%E7%B3%96%E4%B8%BB%E4%B9%89"
	}
	
	,
	
    
	{
		"title" : "《S.h.e   十面埋伏》　2014/08/14　其他",
		"url" : "/m/S.H.E-%E5%8D%81%E9%9D%A2%E5%9F%8B%E4%BC%8F"
	}
	
	,
	
    
	{
		"title" : "《S.h.e   候鸟》　2014/08/14　其他",
		"url" : "/m/S.H.E-%E5%80%99%E9%B8%9F"
	}
	
	,
	
    
	{
		"title" : "《S.h.e   你曾是少年》　2014/08/14　其他",
		"url" : "/m/S.H.E-%E4%BD%A0%E6%9B%BE%E6%98%AF%E5%B0%91%E5%B9%B4"
	}
	
	,
	
    
	{
		"title" : "《S.h.e   他还是不懂》　2014/08/14　其他",
		"url" : "/m/S.H.E-%E4%BB%96%E8%BF%98%E6%98%AF%E4%B8%8D%E6%87%82"
	}
	
	,
	
    
	{
		"title" : "《S.h.e   五月天》　2014/08/14　其他",
		"url" : "/m/S.H.E-%E4%BA%94%E6%9C%88%E5%A4%A9"
	}
	
	,
	
    
	{
		"title" : "《S.h.e   中国话》　2014/08/14　其他",
		"url" : "/m/S.H.E-%E4%B8%AD%E5%9B%BD%E8%AF%9D"
	}
	
	,
	
    
	{
		"title" : "《S.h.e   不想长大》　2014/08/14　其他",
		"url" : "/m/S.H.E-%E4%B8%8D%E6%83%B3%E9%95%BF%E5%A4%A7"
	}
	
	,
	
    
	{
		"title" : "《S.h.e   一眼万年》　2014/08/14　其他",
		"url" : "/m/S.H.E-%E4%B8%80%E7%9C%BC%E4%B8%87%E5%B9%B4"
	}
	
	,
	
    
	{
		"title" : "《S.h.e   super star》　2014/08/14　其他",
		"url" : "/m/S.H.E-Super-Star"
	}
	
	,
	
    
	{
		"title" : "《S.h.e   shero》　2014/08/14　其他",
		"url" : "/m/S.H.E-Shero"
	}
	
	,
	
    
	{
		"title" : "《S.h.e   ring ring ring》　2014/08/14　其他",
		"url" : "/m/S.H.E-Ring-Ring-Ring"
	}
	
	,
	
    
	{
		"title" : "《Rag'n'bone man   skin》　2014/08/14　其他",
		"url" : "/m/Rag'N'Bone-Man-Skin"
	}
	
	,
	
    
	{
		"title" : "《Olly murs   that girl》　2014/08/14　其他",
		"url" : "/m/Olly-Murs-That-Girl"
	}
	
	,
	
    
	{
		"title" : "《Maroon 5 _ christina aguilera   moves like jagger》　2014/08/14　其他",
		"url" : "/m/Maroon-5-_-Christina-Aguilera-Moves-Like-Jagger"
	}
	
	,
	
    
	{
		"title" : "《M2m   the day you went away》　2014/08/14　其他",
		"url" : "/m/M2M-The-Day-You-Went-Away"
	}
	
	,
	
    
	{
		"title" : "《M2m   pretty boy》　2014/08/14　其他",
		"url" : "/m/M2M-Pretty-Boy"
	}
	
	,
	
    
	{
		"title" : "《Kelly clarkson   stronger (what doesn't kill you)》　2014/08/14　其他",
		"url" : "/m/Kelly-Clarkson-Stronger-(What-Doesn't-Kill-You)"
	}
	
	,
	
    
	{
		"title" : "《Joel hanson   traveling light》　2014/08/14　其他",
		"url" : "/m/Joel-Hanson-Traveling-Light"
	}
	
	,
	
    
	{
		"title" : "《Jam   七月上》　2014/08/14　其他",
		"url" : "/m/Jam-%E4%B8%83%E6%9C%88%E4%B8%8A"
	}
	
	,
	
    
	{
		"title" : "《J.fla   shape of you》　2014/08/14　其他",
		"url" : "/m/J.Fla-Shape-of-You"
	}
	
	,
	
    
	{
		"title" : "《Ice paper   心如止水》　2014/08/14　其他",
		"url" : "/m/Ice-Paper-%E5%BF%83%E5%A6%82%E6%AD%A2%E6%B0%B4"
	}
	
	,
	
    
	{
		"title" : "《In K、王忻辰、苏星婕   落日与晚风》　2014/08/14　其他",
		"url" : "/m/IN-K-%E7%8E%8B%E5%BF%BB%E8%BE%B0-%E8%8B%8F%E6%98%9F%E5%A9%95-%E8%90%BD%E6%97%A5%E4%B8%8E%E6%99%9A%E9%A3%8E"
	}
	
	,
	
    
	{
		"title" : "《Hita   醉红绡》　2014/08/14　其他",
		"url" : "/m/HITA-%E9%86%89%E7%BA%A2%E7%BB%A1"
	}
	
	,
	
    
	{
		"title" : "《Hita   赤伶》　2014/08/14　其他",
		"url" : "/m/HITA-%E8%B5%A4%E4%BC%B6"
	}
	
	,
	
    
	{
		"title" : "《G_e_m_ 邓紫棋 _ 张靓颖   雨蝶 (live)》　2014/08/14　其他",
		"url" : "/m/G_E_M_-%E9%82%93%E7%B4%AB%E6%A3%8B-_-%E5%BC%A0%E9%9D%93%E9%A2%96-%E9%9B%A8%E8%9D%B6-(Live)"
	}
	
	,
	
    
	{
		"title" : "《G.e.m. 邓紫棋、王者荣耀   无双的王者》　2014/08/14　其他",
		"url" : "/m/G.E.M.-%E9%82%93%E7%B4%AB%E6%A3%8B-%E7%8E%8B%E8%80%85%E8%8D%A3%E8%80%80-%E6%97%A0%E5%8F%8C%E7%9A%84%E7%8E%8B%E8%80%85"
	}
	
	,
	
    
	{
		"title" : "《G.e.m. 邓紫棋   超能力》　2014/08/14　其他",
		"url" : "/m/G.E.M.-%E9%82%93%E7%B4%AB%E6%A3%8B-%E8%B6%85%E8%83%BD%E5%8A%9B"
	}
	
	,
	
    
	{
		"title" : "《G.e.m. 邓紫棋   画 (live piano session ⅱ)》　2014/08/14　其他",
		"url" : "/m/G.E.M.-%E9%82%93%E7%B4%AB%E6%A3%8B-%E7%94%BB-(Live-Piano-Session-)"
	}
	
	,
	
    
	{
		"title" : "《G.e.m. 邓紫棋   泡沫》　2014/08/14　其他",
		"url" : "/m/G.E.M.-%E9%82%93%E7%B4%AB%E6%A3%8B-%E6%B3%A1%E6%B2%AB"
	}
	
	,
	
    
	{
		"title" : "《G.e.m. 邓紫棋   来自天堂的魔鬼》　2014/08/14　其他",
		"url" : "/m/G.E.M.-%E9%82%93%E7%B4%AB%E6%A3%8B-%E6%9D%A5%E8%87%AA%E5%A4%A9%E5%A0%82%E7%9A%84%E9%AD%94%E9%AC%BC"
	}
	
	,
	
    
	{
		"title" : "《G.e.m. 邓紫棋   我的秘密》　2014/08/14　其他",
		"url" : "/m/G.E.M.-%E9%82%93%E7%B4%AB%E6%A3%8B-%E6%88%91%E7%9A%84%E7%A7%98%E5%AF%86"
	}
	
	,
	
    
	{
		"title" : "《G.e.m. 邓紫棋   多远都要在一起》　2014/08/14　其他",
		"url" : "/m/G.E.M.-%E9%82%93%E7%B4%AB%E6%A3%8B-%E5%A4%9A%E8%BF%9C%E9%83%BD%E8%A6%81%E5%9C%A8%E4%B8%80%E8%B5%B7"
	}
	
	,
	
    
	{
		"title" : "《G.e.m. 邓紫棋   句号》　2014/08/14　其他",
		"url" : "/m/G.E.M.-%E9%82%93%E7%B4%AB%E6%A3%8B-%E5%8F%A5%E5%8F%B7"
	}
	
	,
	
    
	{
		"title" : "《G.e.m. 邓紫棋   再见》　2014/08/14　其他",
		"url" : "/m/G.E.M.-%E9%82%93%E7%B4%AB%E6%A3%8B-%E5%86%8D%E8%A7%81"
	}
	
	,
	
    
	{
		"title" : "《G.e.m. 邓紫棋   光年之外》　2014/08/14　其他",
		"url" : "/m/G.E.M.-%E9%82%93%E7%B4%AB%E6%A3%8B-%E5%85%89%E5%B9%B4%E4%B9%8B%E5%A4%96"
	}
	
	,
	
    
	{
		"title" : "《G.e.m. 邓紫棋   倒数》　2014/08/14　其他",
		"url" : "/m/G.E.M.-%E9%82%93%E7%B4%AB%E6%A3%8B-%E5%80%92%E6%95%B0"
	}
	
	,
	
    
	{
		"title" : "《G.e.m. 邓紫棋   你把我灌醉》　2014/08/14　其他",
		"url" : "/m/G.E.M.-%E9%82%93%E7%B4%AB%E6%A3%8B-%E4%BD%A0%E6%8A%8A%E6%88%91%E7%81%8C%E9%86%89"
	}
	
	,
	
    
	{
		"title" : "《G.e.m. 邓紫棋   两个自己》　2014/08/14　其他",
		"url" : "/m/G.E.M.-%E9%82%93%E7%B4%AB%E6%A3%8B-%E4%B8%A4%E4%B8%AA%E8%87%AA%E5%B7%B1"
	}
	
	,
	
    
	{
		"title" : "《G.e.m. 邓紫棋   两个你》　2014/08/14　其他",
		"url" : "/m/G.E.M.-%E9%82%93%E7%B4%AB%E6%A3%8B-%E4%B8%A4%E4%B8%AA%E4%BD%A0"
	}
	
	,
	
    
	{
		"title" : "《Fall out boy   uma thurman》　2014/08/14　其他",
		"url" : "/m/Fall-Out-Boy-Uma-Thurman"
	}
	
	,
	
    
	{
		"title" : "《Fall out boy   the phoenix》　2014/08/14　其他",
		"url" : "/m/Fall-Out-Boy-The-Phoenix"
	}
	
	,
	
    
	{
		"title" : "《Fall out boy   centuries》　2014/08/14　其他",
		"url" : "/m/Fall-Out-Boy-Centuries"
	}
	
	,
	
    
	{
		"title" : "《Dream   get over》　2014/08/14　其他",
		"url" : "/m/Dream-Get-Over"
	}
	
	,
	
    
	{
		"title" : "《Crayon pop (크레용팝)   어이 (uh Ee)》　2014/08/14　其他",
		"url" : "/m/Crayon-Pop-(%E1%84%8F%E1%85%B3%E1%84%85%E1%85%A6%E1%84%8B%E1%85%AD%E1%86%BC%E1%84%91%E1%85%A1%E1%86%B8)-%E1%84%8B%E1%85%A5%E1%84%8B%E1%85%B5-(Uh-ee)"
	}
	
	,
	
    
	{
		"title" : "《Charlie puth   we don't talk anymore》　2014/08/14　其他",
		"url" : "/m/Charlie-Puth-We-Don't-Talk-Anymore"
	}
	
	,
	
    
	{
		"title" : "《Critty _ 司夏   杏花弦外雨》　2014/08/14　其他",
		"url" : "/m/CRITTY-_-%E5%8F%B8%E5%A4%8F-%E6%9D%8F%E8%8A%B1%E5%BC%A6%E5%A4%96%E9%9B%A8"
	}
	
	,
	
    
	{
		"title" : "《Critty   轮回之境》　2014/08/14　其他",
		"url" : "/m/CRITTY-%E8%BD%AE%E5%9B%9E%E4%B9%8B%E5%A2%83"
	}
	
	,
	
    
	{
		"title" : "《Critty   心若为城》　2014/08/14　其他",
		"url" : "/m/CRITTY-%E5%BF%83%E8%8B%A5%E4%B8%BA%E5%9F%8E"
	}
	
	,
	
    
	{
		"title" : "《By2   爱丫爱丫》　2014/08/14　其他",
		"url" : "/m/BY2-%E7%88%B1%E4%B8%AB%E7%88%B1%E4%B8%AB"
	}
	
	,
	
    
	{
		"title" : "《By2   爱上你》　2014/08/14　其他",
		"url" : "/m/BY2-%E7%88%B1%E4%B8%8A%E4%BD%A0"
	}
	
	,
	
    
	{
		"title" : "《By2   买买买》　2014/08/14　其他",
		"url" : "/m/BY2-%E4%B9%B0%E4%B9%B0%E4%B9%B0"
	}
	
	,
	
    
	{
		"title" : "《By2   不够成熟》　2014/08/14　其他",
		"url" : "/m/BY2-%E4%B8%8D%E5%A4%9F%E6%88%90%E7%86%9F"
	}
	
	,
	
    
	{
		"title" : "《Bwo   sunshine in the rain》　2014/08/14　其他",
		"url" : "/m/BWO-Sunshine-In-The-Rain"
	}
	
	,
	
    
	{
		"title" : "《Beyond   真的爱你》　2014/08/14　其他",
		"url" : "/m/BEYOND-%E7%9C%9F%E7%9A%84%E7%88%B1%E4%BD%A0"
	}
	
	,
	
    
	{
		"title" : "《Beyond   海阔天空》　2014/08/14　其他",
		"url" : "/m/BEYOND-%E6%B5%B7%E9%98%94%E5%A4%A9%E7%A9%BA"
	}
	
	,
	
    
	{
		"title" : "《Beyond   光辉岁月》　2014/08/14　其他",
		"url" : "/m/BEYOND-%E5%85%89%E8%BE%89%E5%B2%81%E6%9C%88"
	}
	
	,
	
    
	{
		"title" : "《Beyond   不再犹豫》　2014/08/14　其他",
		"url" : "/m/BEYOND-%E4%B8%8D%E5%86%8D%E7%8A%B9%E8%B1%AB"
	}
	
	,
	
    
	{
		"title" : "《Ayo97、周思涵   感谢你曾来过》　2014/08/14　其他",
		"url" : "/m/Ayo97-%E5%91%A8%E6%80%9D%E6%B6%B5-%E6%84%9F%E8%B0%A2%E4%BD%A0%E6%9B%BE%E6%9D%A5%E8%BF%87"
	}
	
	,
	
    
	{
		"title" : "《Avril lavigne nicki minaj   dumb blonde》　2014/08/14　其他",
		"url" : "/m/Avril-Lavigne-Nicki-Minaj-Dumb-Blonde"
	}
	
	,
	
    
	{
		"title" : "《Avril lavigne   wish you were here》　2014/08/14　其他",
		"url" : "/m/Avril-Lavigne-Wish-You-Were-Here"
	}
	
	,
	
    
	{
		"title" : "《Avril lavigne   when you're gone》　2014/08/14　其他",
		"url" : "/m/Avril-Lavigne-When-You're-Gone"
	}
	
	,
	
    
	{
		"title" : "《Avril lavigne   tell me it's over》　2014/08/14　其他",
		"url" : "/m/Avril-Lavigne-Tell-Me-It's-Over"
	}
	
	,
	
    
	{
		"title" : "《Avril lavigne   innocence》　2014/08/14　其他",
		"url" : "/m/Avril-Lavigne-Innocence"
	}
	
	,
	
    
	{
		"title" : "《Avril lavigne   head above water》　2014/08/14　其他",
		"url" : "/m/Avril-Lavigne-Head-Above-Water"
	}
	
	,
	
    
	{
		"title" : "《Avril lavigne   girlfriend》　2014/08/14　其他",
		"url" : "/m/Avril-Lavigne-Girlfriend"
	}
	
	,
	
    
	{
		"title" : "《Avril lavigne   complicated》　2014/08/14　其他",
		"url" : "/m/Avril-Lavigne-Complicated"
	}
	
	,
	
    
	{
		"title" : "《Alan walker _ iselin solheim   faded》　2014/08/14　其他",
		"url" : "/m/Alan-Walker-_-Iselin-Solheim-Faded"
	}
	
	,
	
    
	{
		"title" : "《1个球   大雨还在下》　2014/08/14　其他",
		"url" : "/m/1%E4%B8%AA%E7%90%83-%E5%A4%A7%E9%9B%A8%E8%BF%98%E5%9C%A8%E4%B8%8B"
	}
	
    
	]
}
